Workbook

Sheet Resumo
A1: Indicadores N3 — resumo executivo
A2: Base: Backlog Produto - Melhorias, Engenharia de Vídeo, Finalizados, Novas solicitações, Squad Awdio, Squad Conteúdo, Squad Mobile, Squad TV, Squad Web, Suporte & Performance | 1964 chamados únicos (14 duplicados removidos)
A4: Chamados abertos (status ≠ Feito/Cancelado) | B4: 314
A5: Chamados resolvidos (status = Feito) | B5: 1641
A6: Chamados cancelados (fora dos dois indicadores) | B6: 9
A7: Reaberturas/recorrências — confiança Alta | B7: 110
A8: Reaberturas/recorrências — Alta + Média | B8: 137
A9: Taxa de reabertura (Alta+Média / resolvidos) | B9: 0.0835
A12: Incidentes por criticidade
A13: Criticidade | B13: Aberto | C13: Resolvido | D13: Cancelado | E13: Total
A14: P1 | B14: 27 | C14: 208 | D14: 0 | E14: 235
A15: P2 | B15: 88 | C15: 552 | D15: 2 | E15: 642
A16: P3 | B16: 108 | C16: 582 | D16: 2 | E16: 692
A17: P4 | B17: 58 | C17: 241 | D17: 1 | E17: 300
A18: Sem classificação | B18: 33 | C18: 58 | D18: 4 | E18: 95
A20: Top 3 categorias (todos os chamados)
A21: Categoria | B21: Chamados | C21: %
A22: Conteúdo / Catálogo (VOD) | B22: 384 | C22: 0.1955
A23: Canais ao Vivo / EPG | B23: 326 | C23: 0.166
A24: Pacotes / Assinaturas / Integrações | B24: 259 | C24: 0.1319
A26: Detalhes, premissas e limitações: ver abas seguintes e 'Premissas'.

Sheet Abertos x Resolvidos
A1: Por fila (planilha de origem)
A2: Fila | B2: Aberto | C2: Resolvido | D2: Cancelado | E2: Total
A3: Backlog Produto - Melhorias | B3: 19 | C3: 0 | D3: 0 | E3: 19
A4: Engenharia de Vídeo | B4: 8 | C4: 0 | D4: 0 | E4: 8
A5: Finalizados | B5: 21 | C5: 1615 | D5: 4 | E5: 1640
A6: Novas solicitações | B6: 16 | C6: 0 | D6: 0 | E6: 16
A7: Squad Awdio | B7: 15 | C7: 0 | D7: 0 | E7: 15
A8: Squad Conteúdo | B8: 16 | C8: 9 | D8: 4 | E8: 29
A9: Squad Mobile | B9: 77 | C9: 10 | D9: 1 | E9: 88
A10: Squad TV | B10: 59 | C10: 3 | D10: 0 | E10: 62
A11: Squad Web | B11: 14 | C11: 0 | D11: 0 | E11: 14
A12: Suporte & Performance | B12: 69 | C12: 4 | D12: 0 | E12: 73
A14: Abertos por status
A15: Status | B15: Chamados
A16: Aguardando fila | B16: 102
A17: Triagem | B17: 83
A18: Backlog | B18: 54
A19: Em Andamento | B19: 17
A20: Em observação | B20: 13
A21: Aguardando informações | B21: 8
A22: Aguardando terceiro | B22: 6
A23: Aguardando cliente | B23: 6
A24: Pronto pra Lançar | B24: 6
A25: Melhoria | B25: 5
A26: Block | B26: 4
A27: To Do | B27: 3
... A31: Reaberto | B31: 1
A33: Fluxo mensal (abertura pela Data de abertura; resolução pela Data de Conclusão)
A34: Mês | B34: Abertos no mês (entrada) | C34: Resolvidos no mês (Feito c/ data de conclusão)
A35: 2024-05 | B35: 4 | C35: 0
A36: 2024-06 | B36: 3 | C36: 0
A37: 2024-07 | B37: 11 | C37: 0
A38: 2024-08 | B38: 24 | C38: 0
A39: 2024-09 | B39: 39 | C39: 0
A40: 2024-10 | B40: 55 | C40: 0
A41: 2024-11 | B41: 51 | C41: 0
A42: 2024-12 | B42: 35 | C42: 0
A43: 2025-01 | B43: 24 | C43: 0
A44: 2025-02 | B44: 36 | C44: 0
A45: 2025-03 | B45: 25 | C45: 0
A46: 2025-04 | B46: 22 | C46: 0
... A64: 2026-10 | B64: 1 | C64: 0
A66: Resolvidos sem Data de Conclusão: 679; chamados sem Data de abertura: 239 (ficam fora do fluxo mensal).

Sheet Reaberturas
A1: Reaberturas/recorrências detectadas por similaridade de nome (Alta ≥92%, Média ≥85%) — revisar antes de usar
A3: Chamado original (encerrado) | B3: Abertura original | C3: Conclusão original | D3: Chamado reaberto/recorrente | E3: Abertura recorrência | F3: Status recorrência | G3: Criticidade | H3: Serviço | I3: Similaridade (%) | J3: Confiança | K3: Data conclusão original informada?
A4: BKO | Ajuste na data de vencimento plano | B4: 46280 | D4: BKO | Ajuste na data de vencimento plano | E4: 46281 | F4: Feito | G4: P2 | H4: Backoffice (BKO) | I4: 100 | J4: Alta | K4: Não (usou data de abertura)
A5: BKO | Ajuste - Vencimento de Plano | B5: 46198 | C5: 46202 | D5: BKO | Ajuste - Vencimento de Plano | E5: 46210 | F5: Feito | G5: P3 | H5: Backoffice (BKO) | I5: 100 | J5: Alta | K5: Sim
A6: Soft delete - Ligga | B6: 45693 | D6: Soft Delete - Ligga | E6: 45842 | F6: Feito | G6: P2 | H6: Backoffice (BKO) | I6: 100 | J6: Alta | K6: Não (usou data de abertura)
A7: Erro Ao Reproduzir Conteúdo | B7: 45583 | D7: VOD | Erro ao reproduzir conteúdo | E7: 46283 | F7: Aguardando fila | G7: P2 | H7: VOD / Conteúdo | I7: 100 | J7: Alta | K7: Não (usou data de abertura)
A8: Soft Delete usuários Ligga | B8: 45583 | D8: Soft Delete usuários Ligga | E8: 45646 | F8: Feito | G8: P2 | H8: Backoffice (BKO) | I8: 100 | J8: Alta | K8: Não (usou data de abertura)
A9: E-mail de redefinição de senha não é enviado | B9: 45610 | D9: E-mail de redefinição de senha não é enviado | E9: 45664 | F9: Feito | G9: P3 | H9: Plataforma Watch (geral) | I9: 100 | J9: Alta | K9: Não (usou data de abertura)
A10: Erro Ao Reproduzir Conteúdo | B10: 45583 | D10: Conteúdo | Erro ao reproduzir conteúdo | E10: 46007 | F10: Feito | G10: P4 | H10: VOD / Conteúdo | I10: 100 | J10: Alta | K10: Não (usou data de abertura)
A11: Mobile | Opções de áudio e legendas não disponíveis | B11: 46013 | C11: 46021 | D11: Mobile/Ligga | Opções de áudio e legendas não disponíveis | E11: 46044 | F11: Feito | G11: P2 | H11: Apps (TV/Roku/Mobile/Web) | I11: 100 | J11: Alta | K11: Sim
A12: Problemas de integração - Integrator EliteSoft. | B12: 45537 | D12: Problemas de integração - Integrator EliteSoft | E12: 45594 | F12: Feito | G12: P3 | H12: API / Integrações | I12: 100 | J12: Alta | K12: Não (usou data de abertura)
A13: BKO | Ajuste - Vencimento de Plano | B13: 46171 | C13: 46192 | D13: BKO | Ajuste - Vencimento de Plano | E13: 46198 | F13: Feito | G13: P1 | H13: Backoffice (BKO) | I13: 100 | J13: Alta | K13: Sim
A14: BKO | Ajuste - Vencimento de Plano | B14: 46171 | C14: 46192 | D14: BKO | Ajuste - Vencimento de Plano | E14: 46195 | F14: Feito | G14: P3 | H14: Backoffice (BKO) | I14: 100 | J14: Alta | K14: Sim
A15: Ajuste de e-mail incorreto no banco | B15: 46198 | C15: 46206 | D15: Ajuste de e-mail incorreto no banco | E15: 46241 | F15: Feito | G15: P2 | H15: Plataforma Watch (geral) | I15: 100 | J15: Alta | K15: Sim
A16: N-MULTIMIDIA | Migração de tickets UOL Banca para Awdio | B16: 45685 | D16: Migração de tickets UOL BANCA para AWDIO | E16: 45793 | F16: Feito | G16: P3 | H16: Awdio | I16: 100 | J16: Alta | K16: Não (usou data de abertura)
A17: Player | Divergência em Limite de acessos simultâneos | B17: 46092 | C17: 46101 | D17: Mobile | Divergência em Limite de acessos simultâneos | E17: 46174 | F17: Feito | G17: P1 | H17: Apps (TV/Roku/Mobile/Web) | I17: 100 | J17: Alta | K17: Sim
A18: Player | Divergência em Limite de acessos simultâneos | B18: 46092 | C18: 46101 | D18: WEB | Divergência em Limite de acessos simultâneos | E18: 46174 | F18: Feito | G18: P1 | H18: Apps (TV/Roku/Mobile/Web) | I18: 100 | J18: Alta | K18: Sim
A19: Correção de cadastro de e-mail com caractere indevido | B19: 46150 | C19: 46153 | D19: Correção de cadastro de e-mail com caractere indevido | E19: 46225 | F19: Feito | G19: P1 | H19: Plataforma Watch (geral) | I19: 100 | J19: Alta | K19: Sim
A20: Solicitação de exclusão de ticket vinculado a pacote fantasma | B20: 46153 | C20: 46153 | D20: Solicitação de exclusão de ticket vinculado a pacote fantasma | E20: 46162 | F20: Feito | G20: P3 | H20: Plataforma Watch (geral) | I20: 100 | J20: Alta | K20: Sim
A21: Solicitação de exclusão de ticket vinculado a pacote fantasma | B21: 46153 | C21: 46153 | D21: BKO | Solicitação de exclusão de ticket vinculado a pacote fantasma | E21: 46170 | F21: Feito | G21: P3 | H21: Backoffice (BKO) | I21: 100 | J21: Alta | K21: Sim
A22: Solicitação de exclusão de ticket vinculado a pacote fantasma | B22: 46153 | C22: 46153 | D22: BKO | Solicitação de exclusão de ticket vinculado a pacote fantasma | E22: 46188 | F22: Feito | G22: P3 | H22: Backoffice (BKO) | I22: 100 | J22: Alta | K22: Sim
A23: Awdio | Rádio contratada não é reproduzida | B23: 46066 | C23: 46091 | D23: Awdio | Radio contratada não é reproduzida | E23: 46094 | F23: Em observação | G23: P2 | H23: Awdio | I23: 100 | J23: Alta | K23: Sim
A24: Solicitação de exclusão de ticket vinculado a pacote fantasma | B24: 46153 | C24: 46153 | D24: BKO | Solicitação de exclusão de ticket vinculado a pacote fantasma | E24: 46234 | F24: Feito | G24: P4 | H24: Backoffice (BKO) | I24: 100 | J24: Alta | K24: Sim
A25: Solicitação de exclusão de ticket vinculado a pacote fantasma | B25: 46153 | C25: 46153 | D25: BKO | Solicitação de exclusão de ticket vinculado a pacote fantasma | E25: 46245 | F25: Feito | G25: P4 | H25: Backoffice (BKO) | I25: 100 | J25: Alta | K25: Sim
A26: BKO | Ajuste - Vencimento de Plano | B26: 46171 | C26: 46192 | D26: BKO | Ajuste - Vencimento de Plano | E26: 46202 | F26: Feito | G26: P2 | H26: Backoffice (BKO) | I26: 100 | J26: Alta | K26: Sim
A27: Erro de login como parceiro - Paramount | B27: 45625 | D27: Erro no login como parceiro - Paramount | E27: 45652 | F27: Feito | G27: P3 | H27: Plataforma Watch (geral) | I27: 100 | J27: Alta | K27: Não (usou data de abertura)
A28: Ajuste de e-mail incorreto no banco | B28: 46198 | C28: 46206 | D28: Ajuste de e-mail incorreto no banco | E28: 46280 | F28: Feito | G28: P2 | H28: Plataforma Watch (geral) | I28: 100 | J28: Alta | K28: Sim
A29: Conteúdo | Erro ao reproduzir conteúdo pelo banner | B29: 46104 | C29: 46104 | D29: VOD | Erro ao reproduzir conteúdo pelo banner | E29: 46167 | F29: Backlog | G29: P4 | H29: Apps (TV/Roku/Mobile/Web) | I29: 100 | J29: Alta | K29: Sim
A30: ROKU | Ícone de canal exibido quebrado | B30: 46029 | C30: 46042 | D30: Roku | Canal exibido com ícone quebrado | E30: 46191 | F30: Feito | G30: P4 | H30: Apps (TV/Roku/Mobile/Web) | I30: 100 | J30: Alta | K30: Sim
A31: Usuário com acesso ativo na MAX pela Watch mesmo após cancelamento | B31: 46020 | C31: 46045 | D31: Usuário com acesso ativo na MAX pela Watch mesmo após cancelamento | E31: 46052 | F31: Feito | G31: P3 | H31: Plataforma Watch (geral) | I31: 100 | J31: Alta | K31: Sim
A32: Conteúdo | Erro ao reproduzir conteúdo pelo banner | B32: 46013 | C32: 46014 | D32: Conteúdo | Erro ao reproduzir conteúdo pelo banner | E32: 46043 | F32: Feito | G32: P3 | H32: VOD / Conteúdo | I32: 100 | J32: Alta | K32: Sim
A33: Conteúdo | Erro ao reproduzir conteúdo pelo banner | B33: 46013 | C33: 46014 | D33: Conteúdo | Erro ao reproduzir conteúdo pelo banner | E33: 46104 | F33: Feito | G33: P3 | H33: VOD / Conteúdo | I33: 100 | J33: Alta | K33: Sim
A34: Conteúdo | Series exibidas com capa quebrada | B34: 46024 | C34: 46041 | D34: Conteúdo | Séries exibidas com capa quebrada | E34: 46071 | F34: Feito | G34: P4 | H34: VOD / Conteúdo | I34: 100 | J34: Alta | K34: Sim
A35: ROKU | Ícone de canal exibido quebrado | B35: 46029 | C35: 46042 | D35: Alares | Canal exibido com ícone quebrado | E35: 46185 | F35: Feito | G35: P3 | H35: Plataforma Watch (geral) | I35: 100 | J35: Alta | K35: Sim
A36: Conteúdo | Erro ao reproduzir conteúdo pelo banner | B36: 46013 | C36: 46014 | D36: Conteúdo | Erro ao reproduzir conteúdo pelo banner | E36: 46031 | F36: Feito | G36: P3 | H36: VOD / Conteúdo | I36: 100 | J36: Alta | K36: Sim
A37: Erro interno ao recuperar senha | B37: 45826 | C37: 45875 | D37: Erro interno ao recuperar senha | E37: 45880 | F37: Feito | G37: P2 | H37: Plataforma Watch (geral) | I37: 100 | J37: Alta | K37: Sim
A38: SoftDelete - SEMPRE INTERNET | B38: 45750 | D38: SoftDelete - SEMPRE INTERNET | E38: 45909 | F38: Feito | G38: P3 | H38: Backoffice (BKO) | I38: 100 | J38: Alta | K38: Não (usou data de abertura)
A39: Paramount - Erro no login como parceiro | B39: 45544 | D39: Erro de login como parceiro - Paramount | E39: 45625 | F39: Feito | G39: P3 | H39: Plataforma Watch (geral) | I39: 100 | J39: Alta | K39: Não (usou data de abertura)
A40: Soft Delete usuários Vero | B40: 45608 | D40: Soft Delete usuários Vero | E40: 45645 | F40: Feito | G40: P2 | H40: Apps (TV/Roku/Mobile/Web) | I40: 100 | J40: Alta | K40: Não (usou data de abertura)
A41: Conteudo | Filmes com nome e sobrenome de atores exibidos separados | B41: 45980 | C41: 45986 | D41: Conteudo | Filmes com nome e sobrenome de atores exibidos separados | E41: 45992 | F41: Feito | G41: P4 | H41: VOD / Conteúdo | I41: 100 | J41: Alta | K41: Sim
A42: GigaTv | Imagem de perfil não é exibida na tela de ativação | B42: 45911 | C42: 45992 | D42: GiGA+ | Imagem de perfil não é exibida na tela de ativação | E42: 46024 | F42: Feito | G42: P4 | H42: Plataforma Watch (geral) | I42: 100 | J42: Alta | K42: Sim
A43: Conteudo | Filmes com nome e sobrenome de atores exibidos separados | B43: 45965 | C43: 45967 | D43: Conteudo | Filmes com nome e sobrenome de atores exibidos separados | E43: 45980 | F43: Feito | G43: P4 | H43: VOD / Conteúdo | I43: 100 | J43: Alta | K43: Sim
A44: Canais ao vivo | Canal listado em filtro incoerente | B44: 45910 | C44: 45982 | D44: Canais ao vivo | Canal listado em filtro incoerente | E44: 46028 | F44: Feito | G44: P4 | H44: Canais ao Vivo / Eng. de Vídeo | I44: 100 | J44: Alta | K44: Sim
A45: Canais ao vivo | Canal listado em filtro incoerente | B45: 45910 | C45: 45982 | D45: Canais ao vivo | Canal listado em filtro incoerente | E45: 46108 | F45: Feito | G45: P4 | H45: Canais ao Vivo / Eng. de Vídeo | I45: 100 | J45: Alta | K45: Sim
A46: INGEST | Capas quebradas na aba "Continuar assistindo" | B46: 46014 | C46: 46042 | D46: Capas quebradas na aba "Continuar assistindo" | E46: 46083 | F46: Feito | G46: P3 | H46: VOD / Conteúdo | I46: 100 | J46: Alta | K46: Sim
A47: Desktop WEB | Ausência dos botões “Disponível no Google Play” e “Baixar na App Store” no rodapé da página | B47: 46269 | D47: Alares WEB | Ausência dos botões "Disponível no Google Play" e "Baixar na App Store" no rodapé da página | E47: 46280 | F47: Em Andamento | G47: P3 | H47: Apps (TV/Roku/Mobile/Web) | I47: 100 | J47: Alta | K47: Não (usou data de abertura)
A48: Conteúdo | Falha na Inicialização de conteúdo VOD | B48: 45896 | C48: 45918 | D48: Conteúdo | Falha na Inicialização de conteúdo VODs | E48: 45943 | F48: Feito | G48: P4 | H48: VOD / Conteúdo | I48: 98.5 | J48: Alta | K48: Sim
A49: Inconsistência de co-brand impede login no Ligga PlayAC | B49: 46059 | C49: 46030 | D49: Inconsistência de co-brand impede login no Ligga Play | E49: 46059 | F49: Feito | G49: P2 | H49: Plataforma Watch (geral) | I49: 97.9 | J49: Alta | K49: Sim
A50: Inconsistência de co-brand impede login no Ligga Play | B50: 46059 | C50: 46030 | D50: Inconsistência de co-brand impede login no Ligga PlayAC | E50: 46059 | F50: Feito | G50: P2 | H50: Plataforma Watch (geral) | I50: 97.9 | J50: Alta | K50: Sim
A51: Conteúdo | VOD exibido sem capa | B51: 46094 | C51: 46100 | D51: Conteúdo | VOD exibidos sem capa | E51: 46105 | F51: Feito | G51: P4 | H51: VOD / Conteúdo | I51: 97.6 | J51: Alta | K51: Sim
A52: TVs | Perfil Kids não carrega conteúdos nas páginas de Filmes e Séries | B52: 46219 | C52: 46223 | D52: iOS | Perfis Kids não carregam conteúdos nas páginas Filmes e Séries | E52: 46279 | F52: Em observação | G52: P2 | H52: Apps (TV/Roku/Mobile/Web) | I52: 97.1 | J52: Alta | K52: Sim
A53: ROKU | Conteúdos exibidos sem capa | B53: 45999 | C53: 46156 | D53: VOD | Conteúdo exibido sem capa | E53: 46184 | F53: Feito | G53: P3 | H53: VOD / Conteúdo | I53: 96.2 | J53: Alta | K53: Sim
A54: Problema de reprodução de canais ao vivo (live-stream-channels) - Vero | B54: 45911 | C54: 45915 | D54: Problema de reprodução de canais ao vivo (live-stream-channels) | E54: 45917 | F54: Feito | G54: P2 | H54: Canais ao Vivo / Eng. de Vídeo | I54: 95.4 | J54: Alta | K54: Sim
A55: Inconsistência de co-brand impede login no Ligga Play | B55: 46059 | C55: 46030 | D55: Inconsistência de co-brand impede login no Ligga Play (copy) | E55: 46073 | F55: Feito | G55: P2 | H55: Plataforma Watch (geral) | I55: 94.9 | J55: Alta | K55: Sim
A56: Canais sem programação no EPG - TV, Mobo e Web. | B56: 45625 | D56: Canais sem programação no EPG - TV, Mobile e Web. | E56: 45642 | F56: Feito | G56: P3 | H56: Canais ao Vivo / Eng. de Vídeo | I56: 94.9 | J56: Alta | K56: Não (usou data de abertura)
A57: Travamentos e erro de player em canais ao vivo – AIWA Android TV | B57: 46090 | C57: 46142 | D57: Travamentos no player em canais ao vivo – AIWA Android TV | E57: 46188 | F57: Em Andamento | G57: P2 | H57: Apps (TV/Roku/Mobile/Web) | I57: 94.8 | J57: Alta | K57: Sim
A58: Canais ao vivo | Erro ao reproduzir canal ao vivo | B58: 45992 | C58: 46014 | D58: WEB iOS | Erro ao reproduzir canais ao vivo | E58: 46195 | F58: Feito | G58: P2 | H58: Canais ao Vivo / Eng. de Vídeo | I58: 94.3 | J58: Alta | K58: Sim
A59: Logout automático após selecionar o perfil | B59: 46217 | D59: Logout automático após seleção de perfil | E59: 46247 | F59: Feito | G59: P1 | H59: Plataforma Watch (geral) | I59: 93.5 | J59: Alta | K59: Não (usou data de abertura)
A60: Migração de acessos - Mottanet | B60: 46127 | C60: 46129 | D60: Migração de acessos MAX - Mottanet | E60: 46149 | F60: Feito | G60: P2 | H60: Backoffice (BKO) | I60: 92.6 | J60: Alta | K60: Sim
A61: BKO | Ajuste - E-mail - DESKTOP | B61: 46205 | C61: 46205 | D61: Ajuste de e-mail incorreto - Desktop | E61: 46227 | F61: Feito | G61: P2 | H61: Apps (TV/Roku/Mobile/Web) | I61: 92 | J61: Alta | K61: Sim
A62: ROKU | Mensagem de erro não é exibida | B62: 46024 | C62: 46203 | D62: Tvs | Mensagem de erro é exibida ao acessar aplicação | E62: 46211 | F62: Feito | G62: P2 | H62: Apps (TV/Roku/Mobile/Web) | I62: 92 | J62: Alta | K62: Sim
A63: Correção de cadastro de e-mail com caractere indevido | B63: 46150 | C63: 46153 | D63: Correção de cadastro de e-mail com caractere indevido - daniel_costa36@yahoo.com.br | E63: 46255 | F63: Feito | G63: P2 | H63: Plataforma Watch (geral) | I63: 92 | J63: Alta | K63: Sim
A64: BKO | Ajuste - Vencimento de Plano | B64: 46202 | C64: 46204 | D64: BKO | Ajuste na data de vencimento plano | E64: 46280 | F64: Feito | G64: P1 | H64: Backoffice (BKO) | I64: 92 | J64: Alta | K64: Sim
A65: Mobile | Mensagem de erro não é exibida | B65: 46034 | C65: 46105 | D65: Roku | Mensagem de erro é exibida ao acessar opções de menu | E65: 46195 | F65: Aguardando fila | G65: P2 | H65: Apps (TV/Roku/Mobile/Web) | I65: 92 | J65: Alta | K65: Sim
A66: Logout automático após selecionar perfil em iOS – LIGGA | B66: 46097 | C66: 46099 | D66: Logout automático após selecionar o perfil | E66: 46217 | F66: Feito | G66: P2 | H66: Plataforma Watch (geral) | I66: 92 | J66: Alta | K66: Sim
A67: Erro Ao Reproduzir Conteúdo | B67: 45583 | D67: Erro ao tentar reproduzir conteúdo - MS Content-Limit | E67: 46190 | F67: Feito | G67: Sem classificação | H67: VOD / Conteúdo | I67: 92 | J67: Alta | K67: Não (usou data de abertura)
A68: Vinculação indevida de e-mails no banco | B68: 46034 | C68: 46038 | D68: Vinculação indevida de e-mails no banco - lukitas8909@gmail.com/veronicabaumbach@hotmail.com | E68: 46100 | F68: Feito | G68: P2 | H68: Plataforma Watch (geral) | I68: 92 | J68: Alta | K68: Sim
A69: Vinculação indevida de e-mails no banco | B69: 46034 | C69: 46038 | D69: Vinculação indevida de e-mails no banco - Desktop | E69: 46092 | F69: Feito | G69: P2 | H69: Apps (TV/Roku/Mobile/Web) | I69: 92 | J69: Alta | K69: Sim
A70: iOS | Watch V4 | Home não carrega corretamente após troca de perfil | B70: 46139 | C70: 46142 | D70: iOS V4 | Home não carrega após troca de perfil | E70: 46195 | F70: Backlog | G70: P3 | H70: Apps (TV/Roku/Mobile/Web) | I70: 92 | J70: Alta | K70: Sim
A71: Inconsistência de acesso HBO após migração entre pacotes | B71: 46112 | C71: 46114 | D71: LIGGA | Migração entre pacotes | E71: 46217 | F71: Feito | G71: Sem classificação | H71: Plataforma Watch (geral) | I71: 92 | J71: Alta | K71: Sim
A72: MundoVoa web em DEV | Erro ao ativar conta | B72: 45617 | D72: Watch | Erro ao ativar conta via mobile | E72: 46155 | F72: Feito | G72: P1 | H72: Apps (TV/Roku/Mobile/Web) | I72: 92 | J72: Alta | K72: Não (usou data de abertura)
A73: Erro Ao Reproduzir Conteúdo | B73: 45583 | D73: Conteúdo | Erro ao reproduzir conteúdo sem imagem | E73: 46113 | F73: Feito | G73: P3 | H73: VOD / Conteúdo | I73: 92 | J73: Alta | K73: Não (usou data de abertura)
A74: Conteúdo | Série Dexter com falha na reprodução de episódio | B74: 45891 | C74: 45898 | D74: Conteúdo | Série com falha na reprodução de episódio | E74: 45908 | F74: Feito | G74: P4 | H74: VOD / Conteúdo | I74: 92 | J74: Alta | K74: Sim
A75: Erro Ao Reproduzir Conteúdo | B75: 45583 | D75: ROKU | Erro de assinatura ao reproduzir conteúdo | E75: 46030 | F75: Feito | G75: P2 | H75: VOD / Conteúdo | I75: 92 | J75: Alta | K75: Não (usou data de abertura)
A76: Ajuste de Base Ligga - Criação / Exclusão | B76: 45810 | D76: Ligga - Exclusão de Base | E76: 45818 | F76: Feito | G76: P2 | H76: Backoffice (BKO) | I76: 92 | J76: Alta | K76: Não (usou data de abertura)
A77: Soft Delete usuários Ligga | B77: 45646 | D77: Soft delete - Ligga | E77: 45693 | F77: Feito | G77: P2 | H77: Backoffice (BKO) | I77: 92 | J77: Alta | K77: Não (usou data de abertura)
A78: GIGA | BKO | Análise de entrega de e-mails transacionais | B78: 46220 | D78: GIGA | SFMC | Análise de falhas de entrega de e-mails transacionais | E78: 46247 | F78: Feito | G78: P1 | H78: API / Integrações | I78: 92 | J78: Alta | K78: Não (usou data de abertura)
A79: Ajuste de Base Ligga - Criação / Exclusão | B79: 45810 | D79: [LIGGA] - AJUSTE DE BASE | E79: 45950 | F79: Feito | G79: P2 | H79: Plataforma Watch (geral) | I79: 92 | J79: Alta | K79: Não (usou data de abertura)
A80: Bug - Canais ao vivo na ROKU não abrem | B80: 45884 | C80: 45897 | D80: ROKU | Canais ao vivo que não abrem | E80: 45922 | F80: Feito | G80: P3 | H80: Canais ao Vivo / Eng. de Vídeo | I80: 92 | J80: Alta | K80: Sim
A81: Conteúdo | Series com capas quebradas | B81: 46017 | C81: 46021 | D81: VOD | Episódios apresentam capas duplicadas ou capas quebradas em algumas séries | E81: 46286 | F81: Triagem | G81: P3 | H81: VOD / Conteúdo | I81: 92 | J81: Alta | K81: Sim
A82: Conteúdo | Erro ao reproduzir conteúdo | B82: 46007 | C82: 46014 | D82: Android V4 | Erro ao reproduzir conteúdo ao realizar alteração de classificação indicativa no perfil de usuário | E82: 46099 | F82: Feito | G82: P2 | H82: VOD / Conteúdo | I82: 92 | J82: Alta | K82: Sim
A83: Conteúdo | Erro ao reproduzir conteúdo | B83: 46007 | C83: 46014 | D83: Erro ao reproduzir conteúdo - canais lineares iOS | E83: 46050 | F83: Feito | G83: P2 | H83: Canais ao Vivo / Eng. de Vídeo | I83: 92 | J83: Alta | K83: Sim
A84: Conteúdo | Erro ao reproduzir conteúdo | B84: 46007 | C84: 46014 | D84: Usuário com erro ao reproduzir conteúdo (Bob Esponja) | E84: 46189 | F84: Feito | G84: P1 | H84: VOD / Conteúdo | I84: 92 | J84: Alta | K84: Sim
A85: Conteudo | Nome e sobrenome de atores exibidos separados | B85: 45881 | C85: 45908 | D85: Conteudo | Filmes com nome e sobrenome de atores exibidos separados | E85: 45965 | F85: Feito | G85: P4 | H85: VOD / Conteúdo | I85: 92 | J85: Alta | K85: Sim
A86: ROKU | Erro na reprodução de canais | B86: 45579 | C86: 45881 | D86: Mobile | Android | Falha na reprodução de canais ao vivo - Erro de decoder HEVC | E86: 46289 | F86: Triagem | G86: P3 | H86: Apps (TV/Roku/Mobile/Web) | I86: 92 | J86: Alta | K86: Sim
A87: Conteudo | Nome e sobrenome de atores exibidos separados | B87: 45881 | C87: 45908 | D87: Conteudo | Nome e sobrenome de atores exibidos separados - Adrenalina/O Apocalipse | E87: 45943 | F87: Feito | G87: P4 | H87: VOD / Conteúdo | I87: 92 | J87: Alta | K87: Sim
A88: Revisar o envio de dados para o sentry content-service | B88: 46155 | C88: 46183 | D88: Sentry MS | Revisar envio de dados | E88: 46185 | F88: Feito | G88: P1 | H88: Infra / Plataforma Geral | I88: 92 | J88: Alta | K88: Sim
A89: ROKU | Mensagem de erro não é exibida | B89: 46024 | C89: 46203 | D89: Tvs | Mensagem de erro não é exibida ao realizar login com credenciais invalidas | E89: 46217 | F89: Feito | G89: P2 | H89: Apps (TV/Roku/Mobile/Web) | I89: 92 | J89: Alta | K89: Sim
A90: Vinculação indevida de e-mails no banco | B90: 46034 | C90: 46038 | D90: Vinculação indevida de e-mails no banco - joycebrunat@gmail.com | E90: 46237 | F90: Feito | G90: P2 | H90: Plataforma Watch (geral) | I90: 92 | J90: Alta | K90: Sim
A91: Erro ao adicionar Banners | B91: 45653 | D91: Erro ao adicionar Banners em PROD | E91: 45695 | F91: Feito | G91: P2 | H91: CMS | I91: 92 | J91: Alta | K91: Não (usou data de abertura)
A92: Canais sem programação no EPG - TV, Mobile e Web. | B92: 45642 | D92: Canais ao vivo | Canais sem programação | E92: 46027 | F92: Melhoria | G92: P3 | H92: Canais ao Vivo / Eng. de Vídeo | I92: 92 | J92: Alta | K92: Não (usou data de abertura)
A93: Ajuste de e-mail incorreto no banco | B93: 46198 | C93: 46206 | D93: Ajuste de e-mail incorreto no banco - gabriella.finardim@gmail.com | E93: 46241 | F93: Feito | G93: P2 | H93: Plataforma Watch (geral) | I93: 92 | J93: Alta | K93: Sim
A94: Criação de TAGs - Estúdio OFFGRID | B94: 45653 | D94: Criação de TAGs - Estúdio OFFGRID-DESIMPEDIDOS | E94: 45805 | F94: Feito | G94: P2 | H94: CMS | I94: 92 | J94: Alta | K94: Não (usou data de abertura)
A95: Usuário inativo - Watch | B95: 45762 | D95: Usuário ativo no BackOffice, mas acesso é retornado como inativo - Watch | E95: 46202 | F95: Feito | G95: P1 | H95: Backoffice (BKO) | I95: 92 | J95: Alta | K95: Não (usou data de abertura)
A96: Usuário inativo - Watch | B96: 45762 | D96: Analise de usuário ativo na MAX porem inativo na WATCH | E96: 46098 | F96: Feito | G96: P2 | H96: Plataforma Watch (geral) | I96: 92 | J96: Alta | K96: Não (usou data de abertura)
A97: Vinculação indevida de e-mails no banco | B97: 46034 | C97: 46038 | D97: Vinculação indevida de e-mails no banco - denyfferval@gmail.com | E97: 46233 | F97: Feito | G97: P2 | H97: Plataforma Watch (geral) | I97: 92 | J97: Alta | K97: Sim
A98: Vinculação indevida de e-mails no banco | B98: 46034 | C98: 46038 | D98: Vinculação indevida de e-mails no banco - luisgustavocaris2004@gmail.com | E98: 46122 | F98: Feito | G98: P2 | H98: Plataforma Watch (geral) | I98: 92 | J98: Alta | K98: Sim
A99: Vinculação indevida de e-mails no banco | B99: 46034 | C99: 46038 | D99: Vinculação indevida de e-mails no banco - kuviatoszanacarla@gmail.com | E99: 46042 | F99: Feito | G99: P3 | H99: Plataforma Watch (geral) | I99: 92 | J99: Alta | K99: Sim
A100: Mobile | Mensagem de erro não é exibida | B100: 46034 | C100: 46105 | D100: Roku/V4 | Mensagem de erro de PIN não é exibida na tela "Conecte a sua conta" | E100: 46135 | F100: Feito | G100: Sem classificação | H100: Apps (TV/Roku/Mobile/Web) | I100: 92 | J100: Alta | K100: Sim
A101: Mobile | Mensagem de erro não é exibida | B101: 46034 | C101: 46105 | D101: Mobile iOS V4 | Mensagem de erro ao acessar conteúdo com falha não é exibida | E101: 46167 | F101: Triagem | G101: P3 | H101: Apps (TV/Roku/Mobile/Web) | I101: 92 | J101: Alta | K101: Sim
...

Sheet Reab. por serviço
A1: Serviço | B1: Alta | C1: Média | D1: Total
A2: Plataforma Watch (geral) | B2: 27 | C2: 5 | D2: 32
A3: Backoffice (BKO) | B3: 19 | C3: 9 | D3: 28
A4: Apps (TV/Roku/Mobile/Web) | B4: 22 | C4: 4 | D4: 26
A5: VOD / Conteúdo | B5: 23 | C5: 2 | D5: 25
A6: Canais ao Vivo / Eng. de Vídeo | B6: 11 | C6: 3 | D6: 14
A7: Infra / Plataforma Geral | B7: 1 | C7: 4 | D7: 5
A8: Awdio | B8: 3 | C8: 0 | D8: 3
A9: API / Integrações | B9: 2 | C9: 0 | D9: 2
A10: CMS | B10: 2 | C10: 0 | D10: 2

Sheet Incidentes P1-P3
A1: Incidentes por criticidade × estado
A2: Criticidade | B2: Aberto | C2: Resolvido | D2: Cancelado | E2: Total
A3: P1 | B3: 27 | C3: 208 | D3: 0 | E3: 235
A4: P2 | B4: 88 | C4: 552 | D4: 2 | E4: 642
A5: P3 | B5: 108 | C5: 582 | D5: 2 | E5: 692
A6: P4 | B6: 58 | C6: 241 | D6: 1 | E6: 300
A7: Sem classificação | B7: 33 | C7: 58 | D7: 4 | E7: 95
A9: Entrada mensal por criticidade (Data de abertura)
A10: Mês | B10: P1 | C10: P2 | D10: P3 | E10: P4 | F10: Sem classificação
A11: 2024-05 | B11: 0 | C11: 0 | D11: 3 | E11: 1 | F11: 0
A12: 2024-06 | B12: 0 | C12: 1 | D12: 2 | E12: 0 | F12: 0
A13: 2024-07 | B13: 0 | C13: 2 | D13: 7 | E13: 2 | F13: 0
A14: 2024-08 | B14: 0 | C14: 3 | D14: 14 | E14: 6 | F14: 1
A15: 2024-09 | B15: 0 | C15: 7 | D15: 22 | E15: 10 | F15: 0
A16: 2024-10 | B16: 0 | C16: 12 | D16: 28 | E16: 15 | F16: 0
A17: 2024-11 | B17: 1 | C17: 14 | D17: 31 | E17: 5 | F17: 0
A18: 2024-12 | B18: 1 | C18: 16 | D18: 15 | E18: 3 | F18: 0
A19: 2025-01 | B19: 1 | C19: 10 | D19: 11 | E19: 1 | F19: 1
A20: 2025-02 | B20: 2 | C20: 13 | D20: 19 | E20: 2 | F20: 0
A21: 2025-03 | B21: 0 | C21: 11 | D21: 13 | E21: 1 | F21: 0
A22: 2025-04 | B22: 2 | C22: 6 | D22: 14 | E22: 0 | F22: 0
... A40: 2026-10 | B40: 0 | C40: 1 | D40: 0 | E40: 0 | F40: 0
A42: Tempo de resolução (dias, abertura → conclusão; só chamados Feito com as duas datas)
A43: Criticidade | B43: Chamados | C43: Mediana | D43: Média | E43: P90
A44: P1 | B44: 102 | C44: 7 | D44: 14.7 | E44: 43.3
A45: P2 | B45: 336 | C45: 11 | D45: 23.2 | E45: 55
A46: P3 | B46: 306 | C46: 19.5 | D46: 53.2 | E46: 155.5
A47: P4 | B47: 161 | C47: 27 | D47: 76.5 | E47: 197
A48: Sem classificação | B48: 30 | C48: 3.5 | D48: 21.9 | E48: 23.1

Sheet Categorias
A1: Todos os chamados — ranking de categorias
A2: Categoria | B2: Chamados | C2: % | D2: Top
A3: Conteúdo / Catálogo (VOD) | B3: 384 | C3: 0.1955 | D3: 1
A4: Canais ao Vivo / EPG | B4: 326 | C4: 0.166 | D4: 2
A5: Pacotes / Assinaturas / Integrações | B5: 259 | C5: 0.1319 | D5: 3
A6: Acessos / Autenticação | B6: 208 | C6: 0.1059 | D6: 4
A7: Infraestrutura / Instabilidade | B7: 166 | C7: 0.0845 | D7: 5
A8: Banco de Dados / Manipulação de base | B8: 156 | C8: 0.0794 | D8: 6
A9: Aplicativos / Interface (TV, Mobile, Web) | B9: 103 | C9: 0.0524 | D9: 7
A10: Player / Reprodução | B10: 97 | C10: 0.0494 | D10: 8
A11: Perfis / Controle parental | B11: 78 | C11: 0.0397 | D11: 9
A12: E-mails / Notificações | B12: 45 | C12: 0.0229 | D12: 10
A13: Não classificado | B13: 41 | C13: 0.0209 | D13: 11
A14: Melhorias / Solicitações | B14: 40 | C14: 0.0204 | D14: 12
... A16: Segurança | B16: 27 | C16: 0.0137 | D16: 14
A19: Somente abertos — ranking de categorias
A20: Categoria | B20: Chamados | C20: % | D20: Top
A21: Conteúdo / Catálogo (VOD) | B21: 66 | C21: 0.2102 | D21: 1
A22: Canais ao Vivo / EPG | B22: 64 | C22: 0.2038 | D22: 2
A23: Player / Reprodução | B23: 34 | C23: 0.1083 | D23: 3
A24: Aplicativos / Interface (TV, Mobile, Web) | B24: 30 | C24: 0.0955 | D24: 4
A25: Acessos / Autenticação | B25: 26 | C25: 0.0828 | D25: 5
A26: Perfis / Controle parental | B26: 21 | C26: 0.0669 | D26: 6
A27: Infraestrutura / Instabilidade | B27: 16 | C27: 0.051 | D27: 7
A28: Pacotes / Assinaturas / Integrações | B28: 15 | C28: 0.0478 | D28: 8
A29: Melhorias / Solicitações | B29: 13 | C29: 0.0414 | D29: 9
A30: Não classificado | B30: 10 | C30: 0.0318 | D30: 10
A31: Banco de Dados / Manipulação de base | B31: 9 | C31: 0.0287 | D31: 11
A32: Backoffice / CMS | B32: 4 | C32: 0.0127 | D32: 12
... A34: Segurança | B34: 2 | C34: 0.0064 | D34: 14
A37: Somente resolvidos — ranking de categorias
A38: Categoria | B38: Chamados | C38: % | D38: Top
A39: Conteúdo / Catálogo (VOD) | B39: 313 | C39: 0.1907 | D39: 1
A40: Canais ao Vivo / EPG | B40: 260 | C40: 0.1584 | D40: 2
A41: Pacotes / Assinaturas / Integrações | B41: 244 | C41: 0.1487 | D41: 3
A42: Acessos / Autenticação | B42: 182 | C42: 0.1109 | D42: 4
A43: Infraestrutura / Instabilidade | B43: 150 | C43: 0.0914 | D43: 5
A44: Banco de Dados / Manipulação de base | B44: 146 | C44: 0.089 | D44: 6
A45: Aplicativos / Interface (TV, Mobile, Web) | B45: 72 | C45: 0.0439 | D45: 7
A46: Player / Reprodução | B46: 63 | C46: 0.0384 | D46: 8
A47: Perfis / Controle parental | B47: 57 | C47: 0.0347 | D47: 9
A48: E-mails / Notificações | B48: 41 | C48: 0.025 | D48: 10
A49: Não classificado | B49: 31 | C49: 0.0189 | D49: 11
A50: Backoffice / CMS | B50: 30 | C50: 0.0183 | D50: 12
... A52: Segurança | B52: 25 | C52: 0.0152 | D52: 14
A55: Categoria × Serviço/Produto (todos os chamados)
A56: Serviço | B56: Acessos / Autenticação | C56: Aplicativos / Interface (TV, Mobile, Web) | D56: Backoffice / CMS | E56: Banco de Dados / Manipulação de base | F56: Canais ao Vivo / EPG | G56: Conteúdo / Catálogo (VOD) | H56: E-mails / Notificações | I56: Infraestrutura / Instabilidade | J56: Melhorias / Solicitações | K56: Não classificado | L56: Pacotes / Assinaturas / Integrações | M56: Perfis / Controle parental | N56: Player / Reprodução | O56: Segurança
A57: API / Integrações | B57: 9 | C57: 0 | D57: 0 | E57: 14 | F57: 2 | G57: 2 | H57: 1 | I57: 13 | J57: 1 | K57: 0 | L57: 70 | M57: 0 | N57: 0 | O57: 6
A58: Apps (TV/Roku/Mobile/Web) | B58: 106 | C58: 93 | D58: 0 | E58: 7 | F58: 89 | G58: 76 | H58: 5 | I58: 41 | J58: 13 | K58: 7 | L58: 16 | M58: 33 | N58: 37 | O58: 0
A59: Awdio | B59: 7 | C59: 8 | D59: 0 | E59: 1 | F59: 2 | G59: 8 | H59: 4 | I59: 0 | J59: 0 | K59: 0 | L59: 6 | M59: 0 | N59: 7 | O59: 0
A60: Backoffice (BKO) | B60: 13 | C60: 0 | D60: 18 | E60: 53 | F60: 4 | G60: 10 | H60: 4 | I60: 14 | J60: 1 | K60: 0 | L60: 101 | M60: 1 | N60: 0 | O60: 0
A61: CMS | B61: 2 | C61: 0 | D61: 2 | E61: 2 | F61: 0 | G61: 37 | H61: 0 | I61: 13 | J61: 0 | K61: 0 | L61: 2 | M61: 0 | N61: 0 | O61: 0
A62: Canais ao Vivo / Eng. de Vídeo | B62: 3 | C62: 0 | D62: 0 | E62: 7 | F62: 212 | G62: 2 | H62: 0 | I62: 27 | J62: 0 | K62: 0 | L62: 0 | M62: 11 | N62: 3 | O62: 1
A63: Infra / Plataforma Geral | B63: 1 | C63: 0 | D63: 0 | E63: 12 | F63: 0 | G63: 0 | H63: 0 | I63: 29 | J63: 0 | K63: 1 | L63: 0 | M63: 1 | N63: 0 | O63: 15
A64: Plataforma Watch (geral) | B64: 65 | C64: 2 | D64: 0 | E64: 60 | F64: 13 | G64: 23 | H64: 31 | I64: 22 | J64: 25 | K64: 33 | L64: 62 | M64: 16 | N64: 5 | O64: 4
A65: VOD / Conteúdo | B65: 2 | C65: 0 | D65: 14 | E65: 0 | F65: 4 | G65: 226 | H65: 0 | I65: 7 | J65: 0 | K65: 0 | L65: 2 | M65: 16 | N65: 45 | O65: 1

Sheet Serviços
A1: Serviço | B1: Aberto | C1: Resolvido | D1: Cancelado | E1: Total | F1: P1 | G1: P2 | H1: P3
A2: Apps (TV/Roku/Mobile/Web) | B2: 173 | C2: 348 | D2: 2 | E2: 523 | F2: 47 | G2: 143 | H2: 203
A3: Plataforma Watch (geral) | B3: 34 | C3: 327 | D3: 0 | E3: 361 | F3: 68 | G3: 143 | H3: 90
A4: VOD / Conteúdo | B4: 35 | C4: 277 | D4: 5 | E4: 317 | F4: 22 | G4: 76 | H4: 130
A5: Canais ao Vivo / Eng. de Vídeo | B5: 22 | C5: 243 | D5: 1 | E5: 266 | F5: 35 | G5: 75 | H5: 102
A6: Backoffice (BKO) | B6: 14 | C6: 205 | D6: 0 | E6: 219 | F6: 23 | G6: 86 | H6: 85
A7: API / Integrações | B7: 8 | C7: 110 | D7: 0 | E7: 118 | F7: 20 | G7: 55 | H7: 28
A8: Infra / Plataforma Geral | B8: 7 | C8: 51 | D8: 1 | E8: 59 | F8: 16 | G8: 27 | H8: 14
A9: CMS | B9: 4 | C9: 54 | D9: 0 | E9: 58 | F9: 1 | G9: 22 | H9: 24
A10: Awdio | B10: 17 | C10: 26 | D10: 0 | E10: 43 | F10: 3 | G10: 15 | H10: 16

Sheet Disponibilidade
A1: Disponibilidade por serviço/produto
A3: Meta de SLA | B3: 0.995 | D3: Células amarelas são entradas. Ajuste o período e preencha a coluna F da aba 'Eventos indisponibilidade' com os minutos reais de indisponibilidade (monitoramento/NOC).
A4: Início do período | B4: 46266
A5: Fim do período | B5: 46295
A6: Minutos no período | B6: =(B5-B4+1)*1440
A7: Indisponibilidade permitida (min) | B7: =B6*(1-B3)
A8: Indisponibilidade permitida (h:min) | B8: =TEXT(INT(B7/60),"0")&"h"&TEXT(MOD(ROUND(B7,0),60),"00")&"min"
A10: Serviço / Produto | B10: Meta SLA | C10: Permitido no período | D10: Eventos candidatos no período | E10: Eventos com duração informada | F10: Indisponibilidade apurada (min) | G10: Disponibilidade apurada | H10: Indisponibilidade apurada (h:min) | I10: Situação
A11: API / Integrações | B11: =$B$3 | C11: =$B$8 | D11: =COUNTIFS('Eventos indisponibilidade'!$B$2:$B$53,A11,'Eventos indisponibilidade'!$D$2:$D$53,">="&$B$4,'Eventos indisponibilidade'!$D$2:$D$53,"<="&$B$5) | E11: =COUNTIFS('Eventos indisponibilidade'!$B$2:$B$53,A11,'Eventos indisponibilidade'!$F$2:$F$53,">0",'Eventos indisponibilidade'!$D$2:$D$53,">="&$B$4,'Eventos indisponibilidade'!$D$2:$D$53,"<="&$B$5) | F11: =SUMIFS('Eventos indisponibilidade'!$F$2:$F$53,'Eventos indisponibilidade'!$B$2:$B$53,A11,'Eventos indisponibilidade'!$D$2:$D$53,">="&$B$4,'Eventos indisponibilidade'!$D$2:$D$53,"<="&$B$5) | G11: =IF(E11=0,IF(D11=0,1,"n/d"),1-F11/$B$6) | H11: =TEXT(INT(F11/60),"0")&"h"&TEXT(MOD(ROUND(F11,0),60),"00")&"min" | I11: =IF(G11="n/d","Sem duração informada",IF(F11<=$B$7,"Dentro do SLA","Estourou o SLA"))
A12: Apps (TV/Roku/Mobile/Web) | B12: =$B$3 | C12: =$B$8 | D12: =COUNTIFS('Eventos indisponibilidade'!$B$2:$B$53,A12,'Eventos indisponibilidade'!$D$2:$D$53,">="&$B$4,'Eventos indisponibilidade'!$D$2:$D$53,"<="&$B$5) | E12: =COUNTIFS('Eventos indisponibilidade'!$B$2:$B$53,A12,'Eventos indisponibilidade'!$F$2:$F$53,">0",'Eventos indisponibilidade'!$D$2:$D$53,">="&$B$4,'Eventos indisponibilidade'!$D$2:$D$53,"<="&$B$5) | F12: =SUMIFS('Eventos indisponibilidade'!$F$2:$F$53,'Eventos indisponibilidade'!$B$2:$B$53,A12,'Eventos indisponibilidade'!$D$2:$D$53,">="&$B$4,'Eventos indisponibilidade'!$D$2:$D$53,"<="&$B$5) | G12: =IF(E12=0,IF(D12=0,1,"n/d"),1-F12/$B$6) | H12: =TEXT(INT(F12/60),"0")&"h"&TEXT(MOD(ROUND(F12,0),60),"00")&"min" | I12: =IF(G12="n/d","Sem duração informada",IF(F12<=$B$7,"Dentro do SLA","Estourou o SLA"))
A13: Awdio | B13: =$B$3 | C13: =$B$8 | D13: =COUNTIFS('Eventos indisponibilidade'!$B$2:$B$53,A13,'Eventos indisponibilidade'!$D$2:$D$53,">="&$B$4,'Eventos indisponibilidade'!$D$2:$D$53,"<="&$B$5) | E13: =COUNTIFS('Eventos indisponibilidade'!$B$2:$B$53,A13,'Eventos indisponibilidade'!$F$2:$F$53,">0",'Eventos indisponibilidade'!$D$2:$D$53,">="&$B$4,'Eventos indisponibilidade'!$D$2:$D$53,"<="&$B$5) | F13: =SUMIFS('Eventos indisponibilidade'!$F$2:$F$53,'Eventos indisponibilidade'!$B$2:$B$53,A13,'Eventos indisponibilidade'!$D$2:$D$53,">="&$B$4,'Eventos indisponibilidade'!$D$2:$D$53,"<="&$B$5) | G13: =IF(E13=0,IF(D13=0,1,"n/d"),1-F13/$B$6) | H13: =TEXT(INT(F13/60),"0")&"h"&TEXT(MOD(ROUND(F13,0),60),"00")&"min" | I13: =IF(G13="n/d","Sem duração informada",IF(F13<=$B$7,"Dentro do SLA","Estourou o SLA"))
A14: Backoffice (BKO) | B14: =$B$3 | C14: =$B$8 | D14: =COUNTIFS('Eventos indisponibilidade'!$B$2:$B$53,A14,'Eventos indisponibilidade'!$D$2:$D$53,">="&$B$4,'Eventos indisponibilidade'!$D$2:$D$53,"<="&$B$5) | E14: =COUNTIFS('Eventos indisponibilidade'!$B$2:$B$53,A14,'Eventos indisponibilidade'!$F$2:$F$53,">0",'Eventos indisponibilidade'!$D$2:$D$53,">="&$B$4,'Eventos indisponibilidade'!$D$2:$D$53,"<="&$B$5) | F14: =SUMIFS('Eventos indisponibilidade'!$F$2:$F$53,'Eventos indisponibilidade'!$B$2:$B$53,A14,'Eventos indisponibilidade'!$D$2:$D$53,">="&$B$4,'Eventos indisponibilidade'!$D$2:$D$53,"<="&$B$5) | G14: =IF(E14=0,IF(D14=0,1,"n/d"),1-F14/$B$6) | H14: =TEXT(INT(F14/60),"0")&"h"&TEXT(MOD(ROUND(F14,0),60),"00")&"min" | I14: =IF(G14="n/d","Sem duração informada",IF(F14<=$B$7,"Dentro do SLA","Estourou o SLA"))
A15: CMS | B15: =$B$3 | C15: =$B$8 | D15: =COUNTIFS('Eventos indisponibilidade'!$B$2:$B$53,A15,'Eventos indisponibilidade'!$D$2:$D$53,">="&$B$4,'Eventos indisponibilidade'!$D$2:$D$53,"<="&$B$5) | E15: =COUNTIFS('Eventos indisponibilidade'!$B$2:$B$53,A15,'Eventos indisponibilidade'!$F$2:$F$53,">0",'Eventos indisponibilidade'!$D$2:$D$53,">="&$B$4,'Eventos indisponibilidade'!$D$2:$D$53,"<="&$B$5) | F15: =SUMIFS('Eventos indisponibilidade'!$F$2:$F$53,'Eventos indisponibilidade'!$B$2:$B$53,A15,'Eventos indisponibilidade'!$D$2:$D$53,">="&$B$4,'Eventos indisponibilidade'!$D$2:$D$53,"<="&$B$5) | G15: =IF(E15=0,IF(D15=0,1,"n/d"),1-F15/$B$6) | H15: =TEXT(INT(F15/60),"0")&"h"&TEXT(MOD(ROUND(F15,0),60),"00")&"min" | I15: =IF(G15="n/d","Sem duração informada",IF(F15<=$B$7,"Dentro do SLA","Estourou o SLA"))
A16: Canais ao Vivo / Eng. de Vídeo | B16: =$B$3 | C16: =$B$8 | D16: =COUNTIFS('Eventos indisponibilidade'!$B$2:$B$53,A16,'Eventos indisponibilidade'!$D$2:$D$53,">="&$B$4,'Eventos indisponibilidade'!$D$2:$D$53,"<="&$B$5) | E16: =COUNTIFS('Eventos indisponibilidade'!$B$2:$B$53,A16,'Eventos indisponibilidade'!$F$2:$F$53,">0",'Eventos indisponibilidade'!$D$2:$D$53,">="&$B$4,'Eventos indisponibilidade'!$D$2:$D$53,"<="&$B$5) | F16: =SUMIFS('Eventos indisponibilidade'!$F$2:$F$53,'Eventos indisponibilidade'!$B$2:$B$53,A16,'Eventos indisponibilidade'!$D$2:$D$53,">="&$B$4,'Eventos indisponibilidade'!$D$2:$D$53,"<="&$B$5) | G16: =IF(E16=0,IF(D16=0,1,"n/d"),1-F16/$B$6) | H16: =TEXT(INT(F16/60),"0")&"h"&TEXT(MOD(ROUND(F16,0),60),"00")&"min" | I16: =IF(G16="n/d","Sem duração informada",IF(F16<=$B$7,"Dentro do SLA","Estourou o SLA"))
A17: Infra / Plataforma Geral | B17: =$B$3 | C17: =$B$8 | D17: =COUNTIFS('Eventos indisponibilidade'!$B$2:$B$53,A17,'Eventos indisponibilidade'!$D$2:$D$53,">="&$B$4,'Eventos indisponibilidade'!$D$2:$D$53,"<="&$B$5) | E17: =COUNTIFS('Eventos indisponibilidade'!$B$2:$B$53,A17,'Eventos indisponibilidade'!$F$2:$F$53,">0",'Eventos indisponibilidade'!$D$2:$D$53,">="&$B$4,'Eventos indisponibilidade'!$D$2:$D$53,"<="&$B$5) | F17: =SUMIFS('Eventos indisponibilidade'!$F$2:$F$53,'Eventos indisponibilidade'!$B$2:$B$53,A17,'Eventos indisponibilidade'!$D$2:$D$53,">="&$B$4,'Eventos indisponibilidade'!$D$2:$D$53,"<="&$B$5) | G17: =IF(E17=0,IF(D17=0,1,"n/d"),1-F17/$B$6) | H17: =TEXT(INT(F17/60),"0")&"h"&TEXT(MOD(ROUND(F17,0),60),"00")&"min" | I17: =IF(G17="n/d","Sem duração informada",IF(F17<=$B$7,"Dentro do SLA","Estourou o SLA"))
A18: Plataforma Watch (geral) | B18: =$B$3 | C18: =$B$8 | D18: =COUNTIFS('Eventos indisponibilidade'!$B$2:$B$53,A18,'Eventos indisponibilidade'!$D$2:$D$53,">="&$B$4,'Eventos indisponibilidade'!$D$2:$D$53,"<="&$B$5) | E18: =COUNTIFS('Eventos indisponibilidade'!$B$2:$B$53,A18,'Eventos indisponibilidade'!$F$2:$F$53,">0",'Eventos indisponibilidade'!$D$2:$D$53,">="&$B$4,'Eventos indisponibilidade'!$D$2:$D$53,"<="&$B$5) | F18: =SUMIFS('Eventos indisponibilidade'!$F$2:$F$53,'Eventos indisponibilidade'!$B$2:$B$53,A18,'Eventos indisponibilidade'!$D$2:$D$53,">="&$B$4,'Eventos indisponibilidade'!$D$2:$D$53,"<="&$B$5) | G18: =IF(E18=0,IF(D18=0,1,"n/d"),1-F18/$B$6) | H18: =TEXT(INT(F18/60),"0")&"h"&TEXT(MOD(ROUND(F18,0),60),"00")&"min" | I18: =IF(G18="n/d","Sem duração informada",IF(F18<=$B$7,"Dentro do SLA","Estourou o SLA"))
A19: VOD / Conteúdo | B19: =$B$3 | C19: =$B$8 | D19: =COUNTIFS('Eventos indisponibilidade'!$B$2:$B$53,A19,'Eventos indisponibilidade'!$D$2:$D$53,">="&$B$4,'Eventos indisponibilidade'!$D$2:$D$53,"<="&$B$5) | E19: =COUNTIFS('Eventos indisponibilidade'!$B$2:$B$53,A19,'Eventos indisponibilidade'!$F$2:$F$53,">0",'Eventos indisponibilidade'!$D$2:$D$53,">="&$B$4,'Eventos indisponibilidade'!$D$2:$D$53,"<="&$B$5) | F19: =SUMIFS('Eventos indisponibilidade'!$F$2:$F$53,'Eventos indisponibilidade'!$B$2:$B$53,A19,'Eventos indisponibilidade'!$D$2:$D$53,">="&$B$4,'Eventos indisponibilidade'!$D$2:$D$53,"<="&$B$5) | G19: =IF(E19=0,IF(D19=0,1,"n/d"),1-F19/$B$6) | H19: =TEXT(INT(F19/60),"0")&"h"&TEXT(MOD(ROUND(F19,0),60),"00")&"min" | I19: =IF(G19="n/d","Sem duração informada",IF(F19<=$B$7,"Dentro do SLA","Estourou o SLA"))
A21: Atenção: 'Disponibilidade = 100%' só aparece quando não há evento candidato no período; 'n/d' indica evento sem duração.

Sheet Eventos indisponibilidade
A1: Chamado | B1: Serviço | C1: Criticidade | D1: Data de abertura | E1: Data de conclusão | F1: Indisponibilidade (min) — PREENCHER | G1: Origem do valor
A2: Carrosseis telecine mobile - Watch | B2: Apps (TV/Roku/Mobile/Web) | C2: P2 | D2: 45526
A3: TV (Todas as brands) - Fechamento de player ao vivo com conexão de rede instável. | B3: Canais ao Vivo / Eng. de Vídeo | C3: P2 | D3: 45567
A4: Falha no endpoint /oauth-api/auth | B4: API / Integrações | C4: P2 | D4: 45614 | E4: 45881
A5: Banners retornam incorretamente | B5: Plataforma Watch (geral) | C5: P2 | D5: 45621
A6: Erro 500 ao criar usuário no Backoffice | B6: Backoffice (BKO) | C6: P2 | D6: 45643
A7: Contas sem acessoa a P+ - Watch | B7: Apps (TV/Roku/Mobile/Web) | C7: P2 | D7: 45670
A8: Android Watch - Instabilidade de navegação. | B8: Apps (TV/Roku/Mobile/Web) | C8: P1 | D8: 45694
A9: Erro ao adicionar Banners em PROD | B9: CMS | C9: P2 | D9: 45695
A10: Backoffice - Opção "Enviar e-mail" retornando erro 500 | B10: Backoffice (BKO) | C10: P2 | D10: 45716
A11: Timeout na consulta de tickets cadastrados via API - RBT Internet | B11: API / Integrações | C11: P2 | D11: 45723
A12: Web - Canais retornando tela preta (Chrome) /Instabilidade | B12: Canais ao Vivo / Eng. de Vídeo | C12: P2 | D12: 45749 | E12: 45881
A13: Indisponibilidade do Aplicativo Watch Brasil na Loja de Aplicativos do Fire Stick | B13: Apps (TV/Roku/Mobile/Web) | C13: P2 | D13: 45789
A14: Erros variados em TVs de marcas distintas – tela preta e carregamento infinito | B14: Apps (TV/Roku/Mobile/Web) | C14: P1 | D14: 45800
A15: Timeout no consumo dos endpoints - APIWEB | B15: API / Integrações | C15: P2 | D15: 45881 | E15: 45891
A16: Commebol | Transmissão dos jogos apresentam instabilidade | B16: Apps (TV/Roku/Mobile/Web) | C16: P2 | D16: 45883 | E16: 45922
A17: Canais ao vivo | Transmissão de canais apresenta instabilidade | B17: Canais ao Vivo / Eng. de Vídeo | C17: P2 | D17: 45883 | E17: 45891
A18: Bug - queda dos canais ao vivo 15/08 | B18: Canais ao Vivo / Eng. de Vídeo | C18: P1 | D18: 45884 | E18: 45888
A19: BUG canais ao vivo - instabilidade na abertura de canais | B19: Canais ao Vivo / Eng. de Vídeo | C19: P2 | D19: 45888 | E19: 45891
A20: Firestick | Canais ao vivo apresentam tela preta ao serem acessados | B20: Canais ao Vivo / Eng. de Vídeo | C20: P2 | D20: 45889 | E20: 45916
A21: Tela preta ao iniciar o aplicativo em LG | B21: Apps (TV/Roku/Mobile/Web) | C21: P2 | D21: 45901 | E21: 45903
A22: Instabilidade nos canais ao vivo - Alares KA | B22: Canais ao Vivo / Eng. de Vídeo | C22: P2 | D22: 45901 | E22: 45902
A23: Plataforma | Instabilidade na abertura dos apps nas TVs | B23: Apps (TV/Roku/Mobile/Web) | C23: P1 | D23: 45904 | E23: 45959
A24: Tela preta ao acesssar app da Vero em PROD pela Samsung Tizen | B24: Apps (TV/Roku/Mobile/Web) | C24: P1 | D24: 45916 | E24: 45917
A25: Erro 504 no sincronizador de segundos (OTT) | B25: Plataforma Watch (geral) | C25: P2 | D25: 45916 | E25: 45917
A26: Erro 500 ao utilizar a função ''enviar e-mail'' do BackOffice | B26: Backoffice (BKO) | C26: P2 | D26: 45932 | E26: 45996
... A31: Erro 504 - Backoffice | B31: Backoffice (BKO) | C31: P2 | D31: 46030 | E31: 46031
A32: response dos Endpoint de insert na APIWEB exibindo erro 500 | B32: API / Integrações | C32: P2 | D32: 46051
A33: Watch | Canais FAST não são reproduzidos em dispositivos Android TV (tela preta) | B33: Canais ao Vivo / Eng. de Vídeo | C33: P2 | D33: 46076 | E33: 46090
A34: Android TV | Tela preta ao acessar conteúdos no aplicativo | B34: VOD / Conteúdo | C34: P2 | D34: 46104 | E34: 46142
A35: Canais Free não funcionam | ISP Desktop | B35: Canais ao Vivo / Eng. de Vídeo | C35: P2 | D35: 46136 | E35: 46142
A36: iOS | Watch V4 | Canal Globo News não reproduz e exibe mensagem de instabilidade | B36: Apps (TV/Roku/Mobile/Web) | C36: P2 | D36: 46139 | E36: 46139
A37: Erro 504 no Backoffice da Vero | B37: Backoffice (BKO) | C37: P1 | D37: 46183 | E37: 46188
A38: Erro 504 ao acessar a base da VERO | B38: Plataforma Watch (geral) | C38: P2 | D38: 46185 | E38: 46188
A39: Erro 500 ao acessar a base de todos os clientes novos | B39: Backoffice (BKO) | C39: P1 | D39: 46189 | E39: 46190
A40: ott-services-prod-watch com memória em 100% por ~3,5h | B40: Infra / Plataforma Geral | C40: P1 | D40: 46192 | E40: 46206 | F40: 210 | G40: Extraído do nome do chamado (conferir)
A41: Erro 504 (Timeout) na renovação de token - CLICK IP SERVICOS | B41: Plataforma Watch (geral) | C41: P2 | D41: 46195 | E41: 46203
A42: API Erro 504 | RBXSoft | B42: API / Integrações | C42: P2 | D42: 46196 | E42: 46206
A43: TVs | Lentidão ao navegar entre páginas pode resultar em erro "Desculpe, algo deu errado" | B43: Apps (TV/Roku/Mobile/Web) | C43: P2 | D43: 46258
A44: Conteúdo | Instabilidade na reprodução e inconsistências de capa em conteúdos específicos | B44: Apps (TV/Roku/Mobile/Web) | C44: P2 | D44: 46262
A45: GraçaPlay WEB / Backoffice | Instabilidade causada por aumento de erros HTTP 5XX no microsserviço ott-content-limit | B45: Backoffice (BKO) | C45: P1 | D45: 46276
A46: WEB Co-brands | Páginas Welcome apresentam indisponibilidade e exibem mensagem de erro ao acesso | B46: Apps (TV/Roku/Mobile/Web) | C46: P2 | D46: 46280
A47: BKO | Instabilidade com Retorno de Erro 500 | B47: Backoffice (BKO) | C47: P2 | D47: 46288
A48: Erro 504 Gateway Time-out ao acessar o BackOffice | B48: Backoffice (BKO) | C48: P1
A49: Mobile Android+iOS | Evangelizar | Perfil Kids sofre erro 500 ao acessar conteúdo | B49: VOD / Conteúdo | C49: P1
A50: 'Streaming By Watch' ficando entre os perfis na Giga+ (IOS) | B50: Apps (TV/Roku/Mobile/Web) | C50: P2
A51: iOS | Canal Discovery apresenta tela preta durante a reprodução | B51: Apps (TV/Roku/Mobile/Web) | C51: P2
A52: iOS | Canais Discovery apresentam tela preta e mensagem de indisponibilidade durante a reprodução | B52: Canais ao Vivo / Eng. de Vídeo | C52: P2
A53: Instabilidade intermitente na disponibilidade de canais ao vivo e conteúdos VOD | B53: Canais ao Vivo / Eng. de Vídeo | C53: P2

Sheet Premissas
A1: 1. Aberto = status diferente de Feito e Cancelado, em qualquer planilha (inclui itens com status aberto dentro de 'Finalizados').
A2: 2. Resolvido = status 'Feito' em qualquer planilha (inclui itens 'Feito' ainda presentes nas planilhas de abertos).
A3: 3. Cancelado = status 'Cancelado' — mostrado à parte, fora de abertos e resolvidos.
A4: 4. Linhas de total do monday (sem nome) foram descartadas; duplicados (mesmo nome + data de abertura) foram removidos.
A5: 5. Reabertura: chamado B é recorrência de A quando A está 'Feito', B foi aberto depois da conclusão de A (ou da abertura de A, se não há conclusão) e os nomes têm similaridade ≥ 85% (prefixo antes do '|' e palavras vazias ignorados). Confiança Alta ≥ 92%.
A6: 6. A coluna 'Quantidade GLPI' NÃO foi usada como reabertura.
A7: 7. Criticidade (P1–P4) vem da coluna 'Criticidade'; vazios ficam 'Sem classificação'.
A8: 8. Categoria: grupo/título do chamado por palavras-chave; quando não casam, usa a coluna 'Tipo' do monday; senão 'Não classificado'. É heurística — conferir.
A9: 9. Serviço/Produto: fila de origem (Awdio, Eng. de Vídeo, Conteúdo), depois Cliente/Plataforma, palavras do título e Device. É heurística.
A10: 10. Disponibilidade: as planilhas só têm datas (sem hora) e nenhuma duração de indisponibilidade; por isso o % não pode ser apurado automaticamente. A aba traz a estrutura (meta 99,5% = 3h43min em 31 dias) e eventos candidatos (P1/P2 com termos de instabilidade); basta informar os minutos reais.

Sheet Base consolidada
A1: Fila | B1: Nome | C1: Estado | D1: Status | E1: Prioridade_N | F1: TIPO N3 | G1: Categoria | H1: Serviço | I1: Cliente/Plataforma | J1: Device | K1: Tipo | L1: Time | M1: Grupo | N1: Data de abertura | O1: Data de Conclusão | P1: Mês abertura | Q1: Mês conclusão
A2: Backlog Produto - Melhorias | B2: Melhoria | Implementação de mensagem com link para NPS no BackOffice | C2: Aberto | D2: Aguardando informações | E2: P2 | F2: Melhorias de produto | G2: Backoffice / CMS | H2: Backoffice (BKO) | L2: Aguardando triagem | N2: 46230 | P2: 2026-07
A3: Backlog Produto - Melhorias | B3: Melhoria | Consulta de envio de e-mails com segregação por ISP | C3: Aberto | D3: Aguardando fila | E3: P3 | F3: Melhorias de produto | G3: E-mails / Notificações | H3: Plataforma Watch (geral) | I3: ISP | J3: Emails | L3: Produto | N3: 46183 | P3: 2026-06
A4: Backlog Produto - Melhorias | B4: Reclame Aqui | Avaliação de homologação da Apple TV na V4 | C4: Aberto | D4: Aguardando informações | E4: P3 | F4: Melhorias de produto | G4: Melhorias / Solicitações | H4: Apps (TV/Roku/Mobile/Web) | L4: Produto | N4: 46196 | P4: 2026-06
A5: Backlog Produto - Melhorias | B5: Melhoria | Canais ao vivo apresentam faixas de áudio como "Áudio 1" e "Áudio 2" | C5: Aberto | D5: Aguardando terceiro | E5: P3 | F5: Melhorias de produto | G5: Canais ao Vivo / EPG | H5: Canais ao Vivo / Eng. de Vídeo | I5: TV | J5: TV | L5: Produto | N5: 46197 | P5: 2026-06
A6: Backlog Produto - Melhorias | B6: MELHORIA | Inclusão de opção para fixação de qualidade de vídeo nos devices de TV | C6: Aberto | D6: Triagem | E6: P3 | F6: Melhorias de produto | G6: Player / Reprodução | H6: Apps (TV/Roku/Mobile/Web) | L6: Aguardando triagem | N6: 46260 | P6: 2026-08
A7: Backlog Produto - Melhorias | B7: MELHORIA | Exibição do plano contratado no perfil do cliente | C7: Aberto | D7: Aguardando informações | E7: P3 | F7: Melhorias de produto | G7: Perfis / Controle parental | H7: Plataforma Watch (geral) | L7: Aguardando triagem | N7: 46254 | P7: 2026-08
A8: Backlog Produto - Melhorias | B8: GraçaPlay | Carrosseis exibindo o mesmo catalogo de conteúdos | C8: Aberto | D8: Aguardando fila | E8: P3 | G8: Conteúdo / Catálogo (VOD) | H8: VOD / Conteúdo | L8: Aguardando triagem
A9: Backlog Produto - Melhorias | B9: WEB | Watch V4 | Lentidão durante navegação e interações na plataforma | C9: Aberto | D9: Aguardando informações | E9: P4 | F9: Melhorias de produto | G9: Infraestrutura / Instabilidade | H9: Apps (TV/Roku/Mobile/Web) | L9: Produto | N9: 46139 | P9: 2026-04
A10: Backlog Produto - Melhorias | B10: MELHORIA | Personalização da mensagem de ativação via SMS | C10: Aberto | D10: Backlog | E10: P4 | F10: Melhorias de produto | G10: Pacotes / Assinaturas / Integrações | H10: Plataforma Watch (geral) | L10: Produto | N10: 46195 | P10: 2026-06
A11: Backlog Produto - Melhorias | B11: Perfis de usuário | Perfil excluído continua ativo na plataforma | C11: Aberto | D11: Melhoria | E11: P4 | F11: Melhorias de produto | G11: Perfis / Controle parental | H11: Plataforma Watch (geral) | L11: Produto | N11: 45902 | P11: 2025-09
A12: Backlog Produto - Melhorias | B12: Sugestão de melhoria - Vinheta Watch | C12: Aberto | D12: Melhoria | E12: P4 | F12: Melhorias de produto | G12: Conteúdo / Catálogo (VOD) | H12: Plataforma Watch (geral) | I12: Watch | J12: Não se aplica | K12: Conteúdo | L12: Produto | N12: 45897 | P12: 2025-08
A13: Backlog Produto - Melhorias | B13: Sugestão de melhoria - Canais ao vivo | C13: Aberto | D13: Aguardando terceiro | E13: P4 | F13: Melhorias de produto | G13: Canais ao Vivo / EPG | H13: Canais ao Vivo / Eng. de Vídeo | I13: Watch | J13: Não se aplica | K13: Canais ao Vivo | L13: Produto | N13: 45889 | P13: 2025-08
A14: Backlog Produto - Melhorias | B14: Recuperação de perfil excluído remove senha de controle parental | C14: Aberto | D14: Melhoria | E14: P4 | F14: Melhorias de produto | G14: Acessos / Autenticação | H14: Plataforma Watch (geral) | L14: Produto | N14: 45887 | P14: 2025-08
A15: Backlog Produto - Melhorias | B15: Sugestão de melhoria – Fixar afiliada Globo por dispositivo (MAC) para casos pontuais | C15: Aberto | D15: Em observação | E15: P4 | F15: Melhorias de produto | G15: Canais ao Vivo / EPG | H15: Canais ao Vivo / Eng. de Vídeo | I15: Watch | J15: Não se aplica | K15: Afiliadas Globo | L15: Produto | N15: 45997 | P15: 2025-12
A16: Backlog Produto - Melhorias | B16: Melhoria | Avaliação de Viabilidade para Implementação de SSO | C16: Aberto | D16: Triagem | E16: P4 | F16: Melhorias de produto | G16: Melhorias / Solicitações | H16: Plataforma Watch (geral) | I16: Watch | J16: All | L16: Aguardando triagem | N16: 46253 | P16: 2026-08
A17: Backlog Produto - Melhorias | B17: Tvs | Adição de Opção de "Jogos" no menu de estatísticas do Brasileirão | C17: Aberto | D17: Aguardando fila | E17: P4 | F17: Melhorias de produto | G17: Aplicativos / Interface (TV, Mobile, Web) | H17: Apps (TV/Roku/Mobile/Web) | L17: Aguardando triagem
A18: Backlog Produto - Melhorias | B18: Sugestão de melhoria – Visualização de telas conectadas | C18: Aberto | D18: Triagem | E18: Sem classificação | F18: Melhorias de produto | G18: Melhorias / Solicitações | H18: Plataforma Watch (geral) | J18: Não se aplica | L18: Produto | N18: 46105 | P18: 2026-03
A19: Backlog Produto - Melhorias | B19: Perfil | Falha ao editar perfil infantil para perfil com PIN | C19: Aberto | D19: Triagem | E19: Sem classificação | F19: Melhorias de produto | G19: Acessos / Autenticação | H19: Plataforma Watch (geral) | J19: Backend | L19: Produto | N19: 45902 | P19: 2025-09
A20: Backlog Produto - Melhorias | B20: Canais ao vivo | Delay durante os jogos | C20: Aberto | D20: Validar | E20: Sem classificação | F20: Melhorias de produto | G20: Canais ao Vivo / EPG | H20: Canais ao Vivo / Eng. de Vídeo | L20: Produto | N20: 46113 | P20: 2026-04
A21: Squad TV | B21: Evolução de Produto | Descrição no Banner Hero | C21: Aberto | D21: Aguardando fila | E21: P1 | F21: Melhorias de produto | G21: Conteúdo / Catálogo (VOD) | H21: Apps (TV/Roku/Mobile/Web) | L21: Aguardando triagem
A22: Squad TV | B22: TV | Brasileirão | Captura e Envio Obrigatório do Nome do Canal no Fluxo de Geração de Leads | C22: Aberto | D22: Aguardando fila | E22: P1 | F22: Demandas de sustentação | G22: Canais ao Vivo / EPG | H22: Apps (TV/Roku/Mobile/Web) | L22: Suporte e Performance
A23: Squad TV | B23: Travamentos no player em canais ao vivo – AIWA Android TV | C23: Aberto | D23: Em Andamento | E23: P2 | F23: Incidentes e Bugs | G23: Player / Reprodução | H23: Apps (TV/Roku/Mobile/Web) | I23: Watch | J23: TV | K23: Player | L23: TV | N23: 46188 | P23: 2026-06
A24: Squad TV | B24: Plataforma V3 | Dificuldade de acesso a canais ao vivo em diferentes dispositivos e co-brands | C24: Aberto | D24: Aguardando fila | E24: P2 | F24: Demandas de sustentação | G24: Canais ao Vivo / EPG | H24: Apps (TV/Roku/Mobile/Web) | L24: TV | N24: 46188 | P24: 2026-06
A25: Squad TV | B25: Roku | Mensagem de erro é exibida ao acessar opções de menu | C25: Aberto | D25: Aguardando fila | E25: P2 | F25: Incidentes e Bugs | G25: Aplicativos / Interface (TV, Mobile, Web) | H25: Apps (TV/Roku/Mobile/Web) | L25: TV | N25: 46195 | P25: 2026-06
A26: Squad TV | B26: Roku | Watch v4 | Falha ao reproduzir canais ao vivo | C26: Aberto | D26: Aguardando fila | E26: P2 | F26: Incidentes e Bugs | G26: Canais ao Vivo / EPG | H26: Apps (TV/Roku/Mobile/Web) | L26: TV | N26: 46150 | P26: 2026-05
A27: Squad TV | B27: TVs | Lentidão ao navegar entre páginas pode resultar em erro "Desculpe, algo deu errado" | C27: Aberto | D27: Aguardando fila | E27: P2 | F27: Incidentes e Bugs | G27: Infraestrutura / Instabilidade | H27: Apps (TV/Roku/Mobile/Web) | L27: TV | N27: 46258 | P27: 2026-08
A28: Squad TV | B28: Conteúdo | Instabilidade na reprodução e inconsistências de capa em conteúdos específicos | C28: Resolvido | D28: Feito | E28: P2 | F28: Incidentes e Bugs | G28: Infraestrutura / Instabilidade | H28: Apps (TV/Roku/Mobile/Web) | L28: Aguardando triagem | N28: 46262 | P28: 2026-08
A29: Squad TV | B29: TCL | Desempenho inferior da aplicação durante navegação e reprodução quando comparado a outros dispositivos Android TV | C29: Aberto | D29: Aguardando fila | E29: P2 | F29: Demandas de sustentação | G29: Player / Reprodução | H29: Apps (TV/Roku/Mobile/Web) | J29: TV TCL | L29: TV | N29: 46260 | P29: 2026-08
A30: Squad TV | B30: Ligga Play V3 | Toshiba | Logout automático após login por e-mail e senha | C30: Aberto | D30: Aguardando fila | E30: P2 | F30: Incidentes e Bugs | G30: Acessos / Autenticação | H30: Apps (TV/Roku/Mobile/Web) | L30: TV | N30: 46260 | P30: 2026-08
A31: Squad TV | B31: V3 | TV LG | Conteúdos não iniciam reprodução e retornam erro de player | C31: Aberto | D31: Triagem | E31: P2 | F31: Incidentes e Bugs | G31: Player / Reprodução | H31: Apps (TV/Roku/Mobile/Web) | I31: Watch | J31: TV LG | L31: Aguardando triagem | N31: 46262 | P31: 2026-08
A32: Squad TV | B32: Degradação de imagem no canal ESPN em Android TV | C32: Aberto | D32: Aguardando fila | E32: P2 | F32: Incidentes e Bugs | G32: Canais ao Vivo / EPG | H32: Apps (TV/Roku/Mobile/Web) | L32: Aguardando triagem | N32: 46286 | P32: 2026-09
A33: Squad TV | B33: TCL TV | Canais ao vivo apresentam interrupções e travamento durante a reprodução | C33: Aberto | D33: Aguardando terceiro | E33: P3 | F33: Incidentes e Bugs | G33: Canais ao Vivo / EPG | H33: Apps (TV/Roku/Mobile/Web) | L33: TV | N33: 46149 | P33: 2026-05
A34: Squad TV | B34: LG | Ação de troca de canais pelo controle não é executada no dispositivo | C34: Aberto | D34: Aguardando fila | E34: P3 | F34: Demandas de sustentação | G34: Canais ao Vivo / EPG | H34: Apps (TV/Roku/Mobile/Web) | L34: TV | N34: 46176 | P34: 2026-06
A35: Squad TV | B35: Roku | Carrossel Sony One não é exibido no dispositivo | C35: Aberto | D35: Aguardando fila | E35: P3 | F35: Demandas de sustentação | G35: Conteúdo / Catálogo (VOD) | H35: Apps (TV/Roku/Mobile/Web) | L35: TV | N35: 46195 | P35: 2026-06
A36: Squad TV | B36: Plataforma V3 | Sessão perde acesso a conteúdos/abas retornando erro genérico | C36: Aberto | D36: Aguardando fila | E36: P3 | F36: Incidentes e Bugs | G36: Acessos / Autenticação | H36: Apps (TV/Roku/Mobile/Web) | J36: TV | L36: TV | N36: 46195 | P36: 2026-06
A37: Squad TV | B37: Roku | Graça Play | Ícones de canais em “Ao Vivo” com baixa resolução em comparação à Home | C37: Aberto | D37: Aguardando fila | E37: P3 | F37: Demandas de sustentação | G37: Canais ao Vivo / EPG | H37: Apps (TV/Roku/Mobile/Web) | J37: RokuTV | L37: TV | N37: 46199 | P37: 2026-06
A38: Squad TV | B38: Android TV | Inconsistência de afiliada Globo entre smartphone e TV Box ZTE | C38: Aberto | D38: Aguardando cliente | E38: P3 | F38: Demandas de sustentação | G38: Canais ao Vivo / EPG | H38: Apps (TV/Roku/Mobile/Web) | I38: TV | J38: Box TV ZTE | L38: TV | N38: 46210 | P38: 2026-07
A39: Squad TV | B39: Logotipo Universal não exibindo nos cards | C39: Aberto | D39: Aguardando fila | E39: P3 | F39: Incidentes e Bugs | G39: Não classificado | H39: Apps (TV/Roku/Mobile/Web) | L39: TV | N39: 46209 | P39: 2026-07
A40: Squad TV | B40: Tvs | Falha ao realizar ação de excluir caracteres de login | C40: Aberto | D40: Aguardando fila | E40: P3 | F40: Demandas de sustentação | G40: Acessos / Autenticação | H40: Apps (TV/Roku/Mobile/Web) | L40: TV | N40: 46213 | P40: 2026-07
A41: Squad TV | B41: TVs | “Continuar Assistindo” não retoma VOD do ponto salvo e reinicia a reprodução | C41: Aberto | D41: Aguardando fila | E41: P3 | F41: Incidentes e Bugs | G41: Player / Reprodução | H41: Apps (TV/Roku/Mobile/Web) | J41: TV | L41: TV | N41: 46216 | P41: 2026-07
A42: Squad TV | B42: Tvs | Ajuste na ação de avançar tempo de VOD | C42: Aberto | D42: Aguardando fila | E42: P3 | F42: Demandas de sustentação | G42: Conteúdo / Catálogo (VOD) | H42: Apps (TV/Roku/Mobile/Web) | L42: TV | N42: 46218 | P42: 2026-07
A43: Squad TV | B43: FireTV | Imcompatibilidade ao tentar instalar aplicação Watch pela appstore(caso isolado) | C43: Aberto | D43: Aguardando fila | E43: P3 | F43: Demandas de sustentação | G43: Não classificado | H43: Apps (TV/Roku/Mobile/Web) | L43: TV
A44: Squad TV | B44: Roku | Ausência de pré-roll ao acessar conteúdo via continuar assistindo | C44: Resolvido | D44: Feito | E44: P3 | F44: Demandas de sustentação | G44: Conteúdo / Catálogo (VOD) | H44: Apps (TV/Roku/Mobile/Web) | L44: TV
A45: Squad TV | B45: Validação de homologação da Watch TV com dispositivos Fire TV Stick utilizando VegaOS | C45: Aberto | D45: Aguardando fila | E45: P3 | F45: Melhorias de produto | G45: Melhorias / Solicitações | H45: Apps (TV/Roku/Mobile/Web) | L45: TV | N45: 46237 | P45: 2026-08
A46: Squad TV | B46: TVs | Texto dos botões “Adicionar à Lista” e “Remover da Lista” não é atualizado após interação | C46: Aberto | D46: Triagem | E46: P3 | F46: Incidentes e Bugs | G46: Aplicativos / Interface (TV, Mobile, Web) | H46: Apps (TV/Roku/Mobile/Web) | L46: TV | N46: 46240 | P46: 2026-08
A47: Squad TV | B47: Tvs | Erro inesperado ao realizar criação de perfil de usuário por um perfil kids | C47: Aberto | D47: Aguardando fila | E47: P3 | F47: Incidentes e Bugs | G47: Perfis / Controle parental | H47: Apps (TV/Roku/Mobile/Web) | L47: TV
A48: Squad TV | B48: TVs | Avanço e retrocesso pela barra de progresso apresentam comportamento inconsistente durante a navegação do conteúdo | C48: Aberto | D48: Aguardando fila | E48: P3 | F48: Melhorias de produto | G48: Conteúdo / Catálogo (VOD) | H48: Apps (TV/Roku/Mobile/Web) | J48: TV | L48: TV | N48: 46248 | P48: 2026-08
A49: Squad TV | B49: Tvs | Flag de "canais ao vivo" não ativa pós criar perfil de usuário kids via TVs | C49: Aberto | D49: Aguardando fila | E49: P3 | F49: Incidentes e Bugs | G49: Perfis / Controle parental | H49: Apps (TV/Roku/Mobile/Web) | J49: TV | L49: Aguardando triagem
A50: Squad TV | B50: TVs | Tela de player é encerrada após usuário apertar botão "Home" do controle remoto | C50: Aberto | D50: Aguardando fila | E50: P3 | F50: Incidentes e Bugs | G50: Player / Reprodução | H50: Apps (TV/Roku/Mobile/Web) | L50: Aguardando triagem
A51: Squad TV | B51: Tvs | Co-brands exibe banner da copa na aba "Brasileirão" | C51: Aberto | D51: Aguardando fila | E51: P3 | F51: Incidentes e Bugs | G51: Conteúdo / Catálogo (VOD) | H51: Apps (TV/Roku/Mobile/Web) | L51: Aguardando triagem
A52: Squad TV | B52: V3 | TV LG | Análise de travamentos em conteúdos VOD e Ao Vivo em TV LG | C52: Aberto | D52: Aguardando fila | E52: P3 | F52: Demandas de sustentação | G52: Canais ao Vivo / EPG | H52: Apps (TV/Roku/Mobile/Web) | I52: Watch | J52: TV LG | L52: Aguardando triagem | N52: 46253 | P52: 2026-08
A53: Squad TV | B53: Tvs | Carrossel sugestões para você não retorna ao acessar aba de pesquisa V3 | C53: Aberto | D53: Aguardando fila | E53: P3 | F53: Incidentes e Bugs | G53: Conteúdo / Catálogo (VOD) | H53: Apps (TV/Roku/Mobile/Web) | L53: Aguardando triagem
A54: Squad TV | B54: Tvs/Roku | Acesso a transmissão de canais ao vivo com classificação indicativa maior que a permitida | C54: Aberto | D54: Aguardando fila | E54: P3 | F54: Incidentes e Bugs | G54: Canais ao Vivo / EPG | H54: Apps (TV/Roku/Mobile/Web) | L54: Aguardando triagem
A55: Squad TV | B55: Roku | Mensagem de erro não é exibida ao acessar canal/VOD que está com falha | C55: Aberto | D55: Triagem | E55: P3 | F55: Incidentes e Bugs | G55: Canais ao Vivo / EPG | H55: Apps (TV/Roku/Mobile/Web) | L55: Aguardando triagem
A56: Squad TV | B56: LG V3 | Lista de canais trava ao alternar navegação entre Magic Remote e controle direcional | C56: Aberto | D56: Aguardando fila | E56: P3 | F56: Incidentes e Bugs | G56: Canais ao Vivo / EPG | H56: Apps (TV/Roku/Mobile/Web) | J56: TV LG | L56: TV | N56: 46268 | P56: 2026-09
A57: Squad TV | B57: TVs | Navegação não preserva posição na grade de conteúdos após retorno da página de detalhes | C57: Aberto | D57: Aguardando fila | E57: P3 | F57: Melhorias de produto | G57: Canais ao Vivo / EPG | H57: Apps (TV/Roku/Mobile/Web) | J57: TV | L57: TV | N57: 46269 | P57: 2026-09
A58: Squad TV | B58: Tvs | Exibição de conteúdos sem filtro "Infantil" pós criar perfil de usuário infantil pelo dispositivo | C58: Aberto | D58: Aguardando fila | E58: P3 | F58: Incidentes e Bugs | G58: Perfis / Controle parental | H58: Apps (TV/Roku/Mobile/Web) | L58: Aguardando triagem
A59: Squad TV | B59: Validação de erro de acesso simultâneo em canal Premiere - Ouvidoria | C59: Aberto | D59: Block | E59: P3 | F59: Incidentes e Bugs | G59: Canais ao Vivo / EPG | H59: Apps (TV/Roku/Mobile/Web) | L59: Suporte e Performance | M59: Análise | N59: 46237 | P59: 2026-08
A60: Squad TV | B60: Roku | Ícones de perfis apresentam baixa resolução em modelos específicos da plataforma | C60: Aberto | D60: Aguardando informações | E60: P3 | F60: Melhorias de produto | G60: Perfis / Controle parental | H60: Apps (TV/Roku/Mobile/Web) | J60: RokuTV | L60: TV | N60: 46279 | P60: 2026-09
A61: Squad TV | B61: TV | Adequação aos erros de acesso simultâneo da V2 do User Consumption | C61: Aberto | D61: Aguardando fila | E61: P3 | G61: Aplicativos / Interface (TV, Mobile, Web) | H61: Apps (TV/Roku/Mobile/Web) | L61: TV
A62: Squad TV | B62: Roku | Logo de estúdio não é exibida nas capas de VODs | C62: Aberto | D62: Aguardando fila | E62: P4 | F62: Demandas de sustentação | G62: Conteúdo / Catálogo (VOD) | H62: Apps (TV/Roku/Mobile/Web) | L62: TV | N62: 46195 | P62: 2026-06
A63: Squad TV | B63: Falha de exibição de vídeo pós-seek - ROKU | C63: Aberto | D63: Aguardando fila | E63: P4 | F63: Incidentes e Bugs | G63: Player / Reprodução | H63: Apps (TV/Roku/Mobile/Web) | I63: Watch | J63: RokuTV | K63: Comportamento | L63: TV | N63: 46122 | P63: 2026-04
A64: Squad TV | B64: Roku | Cursor de texto retorna visualmente ao final do campo durante edição de e-mail e senha | C64: Aberto | D64: Aguardando fila | E64: P4 | F64: Incidentes e Bugs | G64: Acessos / Autenticação | H64: Apps (TV/Roku/Mobile/Web) | J64: RokuTV | L64: TV | N64: 46205 | P64: 2026-07
A65: Squad TV | B65: Tvs | Botões “Continuar” e “Reiniciar” exibem informações de temporada e episódio indevidamente nas co-brands | C65: Aberto | D65: Aguardando fila | E65: P4 | F65: Incidentes e Bugs | G65: Conteúdo / Catálogo (VOD) | H65: Apps (TV/Roku/Mobile/Web) | J65: TV | L65: TV | N65: 46218 | P65: 2026-07
A66: Squad TV | B66: Roku/Giga | Texto de boas vindas da tela inicial não é exibida no dispositivo | C66: Aberto | D66: Triagem | E66: P4 | F66: Incidentes e Bugs | G66: Aplicativos / Interface (TV, Mobile, Web) | H66: Apps (TV/Roku/Mobile/Web) | L66: Aguardando triagem
A67: Squad TV | B67: Tvs | Botão "Ver mais" é exibido no carrossel "Terror Sob Medida" | C67: Aberto | D67: Triagem | E67: P4 | F67: Incidentes e Bugs | G67: Conteúdo / Catálogo (VOD) | H67: Apps (TV/Roku/Mobile/Web) | L67: Aguardando triagem
A68: Squad TV | B68: Tvs | Banners de conteúdos são exibidos sem imagem | C68: Aberto | D68: Triagem | E68: P4 | F68: Incidentes e Bugs | G68: Conteúdo / Catálogo (VOD) | H68: Apps (TV/Roku/Mobile/Web) | L68: Aguardando triagem
A69: Squad TV | B69: Legendas não são exibidas nos canais ao vivo - TV | C69: Aberto | D69: Aguardando fila | E69: Sem classificação | F69: Demandas de sustentação | G69: Canais ao Vivo / EPG | H69: Apps (TV/Roku/Mobile/Web) | L69: TV
A70: Squad TV | B70: Tvs | Função "assistidos recentemente" não é atualizada após acessar canal | C70: Aberto | D70: Pronto pra Lançar | E70: Sem classificação | F70: Demandas de sustentação | G70: Canais ao Vivo / EPG | H70: Apps (TV/Roku/Mobile/Web) | L70: TV | N70: 46136 | P70: 2026-04
A71: Squad TV | B71: Roku/V4 | Código de ativação não é resetado pós tempo de atualização | C71: Aberto | D71: Aguardando fila | E71: Sem classificação | F71: Demandas de sustentação | G71: Acessos / Autenticação | H71: Apps (TV/Roku/Mobile/Web) | L71: TV | M71: Roku | N71: 46135 | P71: 2026-04
A72: Squad TV | B72: TV | Informações sobre o conteúdo sobrepondo os gêneros | C72: Aberto | D72: Aguardando fila | E72: Sem classificação | F72: Incidentes e Bugs | G72: Conteúdo / Catálogo (VOD) | H72: Apps (TV/Roku/Mobile/Web) | L72: TV | N72: 46188 | P72: 2026-06
A73: Squad TV | B73: Melhoria | TV | Destacar episódio em reprodução na seção “Mais Episódios” | C73: Aberto | D73: Aguardando fila | E73: Sem classificação | F73: Melhorias de produto | G73: Player / Reprodução | H73: Apps (TV/Roku/Mobile/Web) | I73: TV | J73: TV | L73: TV | N73: 46196 | P73: 2026-06
A74: Squad TV | B74: Roku | Função “Próximo Episódio” não funciona corretamente na série “1923” | C74: Aberto | D74: Aguardando fila | E74: Sem classificação | F74: Demandas de sustentação | G74: Conteúdo / Catálogo (VOD) | H74: Apps (TV/Roku/Mobile/Web) | J74: RokuTV | L74: TV | N74: 46212 | P74: 2026-07
A75: Squad TV | B75: Roku | Categoria “Favoritos” não é exibida no carrossel de canais ao vivo da Home | C75: Aberto | D75: Backlog | E75: Sem classificação | F75: Demandas de sustentação | G75: Canais ao Vivo / EPG | H75: Apps (TV/Roku/Mobile/Web) | J75: RokuTV | L75: TV | N75: 46212 | P75: 2026-07
A76: Squad TV | B76: Roku | Função “Próximo Episódio” exibe episódio incorreto a partir do segundo episódio de séries | C76: Aberto | D76: Aguardando fila | E76: Sem classificação | F76: Incidentes e Bugs | G76: Conteúdo / Catálogo (VOD) | H76: Apps (TV/Roku/Mobile/Web) | J76: RokuTV | L76: TV | N76: 46217 | P76: 2026-07
A77: Squad TV | B77: TVs | Sessão expirada após longo período em standby exibe erro de carregamento de perfis e força novo login | C77: Aberto | D77: Aguardando fila | E77: Sem classificação | F77: Demandas de sustentação | G77: Acessos / Autenticação | H77: Apps (TV/Roku/Mobile/Web) | J77: TV | L77: TV
A78: Squad TV | B78: Roku | Classificação indicativa ausente em canais ao vivo na grade e no player | C78: Aberto | D78: Triagem | E78: Sem classificação | F78: Incidentes e Bugs | G78: Canais ao Vivo / EPG | H78: Apps (TV/Roku/Mobile/Web) | J78: RokuTV | L78: TV | N78: 46240 | P78: 2026-08
A79: Squad TV | B79: Análise | Sessão não é invalidada imediatamente ao trocar senha | C79: Resolvido | D79: Feito | E79: Sem classificação | F79: Demandas de sustentação | G79: Acessos / Autenticação | H79: Apps (TV/Roku/Mobile/Web) | L79: Aguardando triagem
A80: Squad TV | B80: TVs V4 | Filtros de categorias da Home não alteram os canais exibidos no carrossel de Canais ao Vivo | C80: Aberto | D80: Aguardando fila | E80: P3 | F80: Incidentes e Bugs | G80: Canais ao Vivo / EPG | H80: Apps (TV/Roku/Mobile/Web) | J80: TV | L80: TV | N80: 46293 | P80: 2026-09
A81: Squad TV | B81: FireTV | EPG sem indicador visual de foco no primeiro acesso | C81: Aberto | D81: Aguardando fila | E81: P3 | F81: Incidentes e Bugs | G81: Acessos / Autenticação | H81: Apps (TV/Roku/Mobile/Web) | I81: Watch | J81: Fire TV | L81: Aguardando triagem | N81: 46290 | P81: 2026-09
A82: Squad TV | B82: Roku | Análise de lentidão em Roku Express 3930BR | C82: Aberto | D82: Aguardando fila | E82: P3 | F82: Demandas de sustentação | G82: Infraestrutura / Instabilidade | H82: Apps (TV/Roku/Mobile/Web) | I82: Watch | J82: RokuTV | L82: Aguardando triagem | N82: 46290 | P82: 2026-09
A83: Squad Conteúdo | B83: VOD | Falha em conteúdos de animação | C83: Aberto | D83: To Do | E83: P2 | F83: Incidentes e Bugs | G83: Conteúdo / Catálogo (VOD) | H83: VOD / Conteúdo | I83: Watch | K83: Conteúdo | L83: Scrow | M83: Conteúdo | N83: 46168 | P83: 2026-05
A84: Squad Conteúdo | B84: VOD | Erro ao acessar conteúdo pela aplicação | C84: Resolvido | D84: Feito | E84: P2 | F84: Incidentes e Bugs | G84: Conteúdo / Catálogo (VOD) | H84: VOD / Conteúdo | L84: Awdio | M84: Análise | N84: 46196 | P84: 2026-06
A85: Squad Conteúdo | B85: Conteúdo | VOD “A Sua Aura é Azul: Arthur Bispo do Rosário” não reproduz em nenhuma plataforma | C85: Aberto | D85: Em Andamento | E85: P2 | F85: Incidentes e Bugs | G85: Player / Reprodução | H85: VOD / Conteúdo | L85: Scrow | N85: 46210 | P85: 2026-07
A86: Squad Conteúdo | B86: VOD | Erro ao tentar acessar conteúdo "Natal no salão de beleza" | C86: Resolvido | D86: Feito | E86: P2 | F86: Incidentes e Bugs | G86: Conteúdo / Catálogo (VOD) | H86: VOD / Conteúdo | L86: Awdio | N86: 46216 | P86: 2026-07
A87: Squad Conteúdo | B87: VOD | Divergência de conteúdos visíveis na V3 não aparecem na V4 ao acessar aba Filmes | C87: Aberto | D87: Aguardando terceiro | E87: P2 | F87: Demandas de sustentação | G87: Conteúdo / Catálogo (VOD) | H87: VOD / Conteúdo | L87: Suporte e Performance | M87: Análise | N87: 46204 | P87: 2026-07
A88: Squad Conteúdo | B88: VOD | Falha ao reproduzir conteúdo "Doutor Sono" | C88: Aberto | D88: Triagem | E88: P2 | F88: Incidentes e Bugs | G88: Player / Reprodução | H88: VOD / Conteúdo | L88: Aguardando triagem
A89: Squad Conteúdo | B89: VOD | Conteúdos apresentam capa quebrada e inconsistências de reprodução | C89: Aberto | D89: Triagem | E89: P2 | F89: Incidentes e Bugs | G89: Player / Reprodução | H89: VOD / Conteúdo | L89: Conteúdo | N89: 46287 | P89: 2026-09
A90: Squad Conteúdo | B90: Conteúdo | Episódios faltando em conteúdos (séries com temporadas incompletas ou episódios ausentes) | C90: Aberto | D90: Em Andamento | E90: P3 | F90: Incidentes e Bugs | G90: Conteúdo / Catálogo (VOD) | H90: VOD / Conteúdo | L90: Awdio | N90: 46043 | P90: 2026-01
A91: Squad Conteúdo | B91: Android V4 | Conteúdo descontinuado visível apenas no Android com capa quebrada – “Fominha - Desimpedidos” | C91: Resolvido | D91: Feito | E91: P3 | F91: Incidentes e Bugs | G91: Conteúdo / Catálogo (VOD) | H91: VOD / Conteúdo | L91: Awdio | N91: 46104 | P91: 2026-03
A92: Squad Conteúdo | B92: Tvs | Conteúdos em categorias da área de pesquisa com capa quebrada e erro de reprodução | C92: Resolvido | D92: Feito | E92: P3 | F92: Incidentes e Bugs | G92: Player / Reprodução | H92: VOD / Conteúdo | J92: TV | L92: Awdio | N92: 46057 | P92: 2026-02
A93: Squad Conteúdo | B93: Erro na reprodução de conteúdo | C93: Aberto | D93: Backlog | E93: P3 | F93: Incidentes e Bugs | G93: Player / Reprodução | H93: VOD / Conteúdo | L93: Awdio | N93: 46188 | P93: 2026-06
A94: Squad Conteúdo | B94: Conteúdo | Episódios ausentes em temporadas de séries | C94: Aberto | D94: Em Andamento | E94: P3 | F94: Incidentes e Bugs | G94: Conteúdo / Catálogo (VOD) | H94: VOD / Conteúdo | L94: Awdio | N94: 46204 | P94: 2026-07
A95: Squad Conteúdo | B95: VOD | Logo de estúdio edye não é exibida nas capas de VODs | C95: Cancelado | D95: Cancelado | E95: P3 | F95: Incidentes e Bugs | G95: Conteúdo / Catálogo (VOD) | H95: VOD / Conteúdo | L95: Awdio | N95: 46203 | P95: 2026-06
A96: Squad Conteúdo | B96: Conteúdo | Série “Beavis e Butt-Head” exibe capa incorreta da série “1923” | C96: Resolvido | D96: Feito | E96: P3 | F96: Incidentes e Bugs | G96: Conteúdo / Catálogo (VOD) | H96: VOD / Conteúdo | L96: Suporte e Performance | M96: Imagens | N96: 46241 | P96: 2026-08
A97: Squad Conteúdo | B97: Conteúdo | Série “Que Seja Doce” (ID 15441) apresenta capa quebrada no catálogo | C97: Resolvido | D97: Feito | E97: P3 | F97: Incidentes e Bugs | G97: Conteúdo / Catálogo (VOD) | H97: VOD / Conteúdo | L97: Conteúdo | N97: 46260 | P97: 2026-08
A98: Squad Conteúdo | B98: Conteúdo | "Amor e Outras Drogas" apresenta ambas as faixas de áudio em dublado | C98: Aberto | D98: Triagem | E98: P3 | F98: Incidentes e Bugs | G98: Player / Reprodução | H98: VOD / Conteúdo | L98: Conteúdo | N98: 46267 | P98: 2026-09
A99: Squad Conteúdo | B99: Episódio 9 ausente – Dawson's Creek | C99: Aberto | D99: Em Andamento | E99: P3 | F99: Incidentes e Bugs | G99: Conteúdo / Catálogo (VOD) | H99: VOD / Conteúdo | L99: Conteúdo | N99: 46276 | P99: 2026-09
A100: Squad Conteúdo | B100: VOD | Série "Criativa-mente" (ID: 102707) apresenta capas de episódios cortadas na WEB e iOS | C100: Aberto | D100: Triagem | E100: P3 | F100: Incidentes e Bugs | G100: Conteúdo / Catálogo (VOD) | H100: VOD / Conteúdo | L100: Conteúdo | N100: 46279 | P100: 2026-09
...
